{
  "refurbished_furniture:recipes/misc/slicing/brown_dye_from_rotten_flesh": {
    "criteria": {
      "has_rotten_flesh": "2025-11-22 01:37:15 +0000"
    },
    "done": true
  },
  "refurbished_furniture:recipes/misc/light_electricity_generator": {
    "criteria": {
      "has_iron_ingot": "2025-11-21 22:50:54 +0000"
    },
    "done": true
  },
  "refurbished_furniture:recipes/misc/constructing/birch_basin": {
    "criteria": {
      "has_minecraft:birch_planks": "2025-11-21 22:29:27 +0000"
    },
    "done": true
  },
  "minecraft:recipes/redstone/lever": {
    "criteria": {
      "has_cobblestone": "2025-11-21 22:31:38 +0000"
    },
    "done": true
  },
  "farmersdelight:recipes/cooking/dog_food": {
    "criteria": {
      "has_any_ingredient": "2025-11-21 23:36:40 +0000"
    },
    "done": true
  },
  "refurbished_furniture:recipes/misc/constructing/acacia_toilet": {
    "criteria": {
      "has_minecraft:iron_ingot": "2025-11-21 22:50:54 +0000"
    },
    "done": true
  },
  "farmersdelight:recipes/food/nether_salad": {
    "criteria": {
      "has_bowl": "2025-11-22 01:27:00 +0000"
    },
    "done": true
  },
  "minecraft:recipes/misc/pink_dye_from_pink_petals": {
    "criteria": {
      "has_pink_petals": "2025-11-21 23:09:38 +0000"
    },
    "done": true
  },
  "refurbished_furniture:recipes/misc/constructing/purple_stool": {
    "criteria": {
      "has_planks": "2025-11-21 22:29:21 +0000"
    },
    "done": true
  },
  "farmersdelight:main/place_cooking_pot": {
    "criteria": {
      "cooking_pot": "2025-11-22 00:47:20 +0000"
    },
    "done": true
  },
  "farmersdelight:recipes/cooking/mushroom_rice": {
    "criteria": {
      "has_any_ingredient": "2025-11-21 23:58:05 +0000"
    },
    "done": true
  },
  "minecraft:recipes/decorations/ladder": {
    "criteria": {
      "has_stick": "2025-11-21 22:28:43 +0000"
    },
    "done": true
  },
  "farmersdelight:recipes/misc/iron_nugget_from_blasting_knife": {
    "criteria": {
      "has_iron_knife": "2025-11-22 00:38:53 +0000"
    },
    "done": true
  },
  "waystones:recipes/decorations/black_sharestone": {
    "criteria": {
      "has_warp_stone": "2025-11-21 23:00:22 +0000"
    },
    "done": true
  },
  "refurbished_furniture:recipes/misc/constructing/magenta_trampoline": {
    "criteria": {
      "has_minecraft:iron_ingot": "2025-11-21 22:50:54 +0000"
    },
    "done": true
  },
  "minecraft:recipes/combat/iron_leggings": {
    "criteria": {
      "has_iron_ingot": "2025-11-21 22:50:54 +0000"
    },
    "done": true
  },
  "refurbished_furniture:recipes/misc/constructing/lime_grill": {
    "criteria": {
      "has_minecraft:iron_ingot": "2025-11-21 22:50:54 +0000"
    },
    "done": true
  },
  "vanillatweaks:root": {
    "criteria": {
      "tick": "2025-11-21 22:15:48 +0000"
    },
    "done": true
  },
  "farmersdelight:recipes/food/grilled_salmon": {
    "criteria": {
      "has_salmon": "2025-11-21 22:40:32 +0000"
    },
    "done": true
  },
  "refurbished_furniture:recipes/misc/constructing/blue_stool": {
    "criteria": {
      "has_planks": "2025-11-21 22:29:21 +0000"
    },
    "done": true
  },
  "refurbished_furniture:recipes/misc/constructing/oak_toilet": {
    "criteria": {
      "has_minecraft:oak_planks": "2025-11-21 22:29:21 +0000"
    },
    "done": true
  },
  "refurbished_furniture:recipes/misc/constructing/crimson_lattice_fence": {
    "criteria": {
      "has_minecraft:stick": "2025-11-21 22:28:43 +0000"
    },
    "done": true
  },
  "refurbished_furniture:recipes/misc/slicing/pink_dye_from_pink_petals": {
    "criteria": {
      "has_pink_petals": "2025-11-21 23:09:38 +0000"
    },
    "done": true
  },
  "minecraft:story/obtain_armor": {
    "criteria": {
      "iron_leggings": "2025-11-21 22:50:51 +0000"
    },
    "done": true
  },
  "refurbished_furniture:recipes/misc/constructing/birch_crate": {
    "criteria": {
      "has_minecraft:birch_planks": "2025-11-21 22:29:27 +0000"
    },
    "done": true
  },
  "minecraft:recipes/misc/copper_nugget_from_smelting": {
    "criteria": {
      "has_copper_helmet": "2025-11-21 22:45:28 +0000"
    },
    "done": true
  },
  "refurbished_furniture:recipes/misc/constructing/gray_trampoline": {
    "criteria": {
      "has_minecraft:iron_ingot": "2025-11-21 22:50:54 +0000"
    },
    "done": true
  },
  "refurbished_furniture:recipes/misc/constructing/brown_stool": {
    "criteria": {
      "has_planks": "2025-11-21 22:29:21 +0000"
    },
    "done": true
  },
  "farmersdelight:recipes/cooking/fish_stew": {
    "criteria": {
      "has_any_ingredient": "2025-11-21 22:40:32 +0000"
    },
    "done": true
  },
  "refurbished_furniture:recipes/misc/constructing/jungle_lattice_fence": {
    "criteria": {
      "has_minecraft:stick": "2025-11-21 22:28:43 +0000"
    },
    "done": true
  },
  "minecraft:recipes/building_blocks/cherry_slab": {
    "criteria": {
      "has_planks": "2025-11-22 02:10:07 +0000"
    },
    "done": true
  },
  "refurbished_furniture:recipes/misc/constructing/spruce_table": {
    "criteria": {
      "has_minecraft:spruce_planks": "2025-11-21 22:51:02 +0000"
    },
    "done": true
  },
  "refurbished_furniture:recipes/misc/constructing/mangrove_bath": {
    "criteria": {
      "has_minecraft:iron_ingot": "2025-11-21 22:50:54 +0000"
    },
    "done": true
  },
  "refurbished_furniture:recipes/misc/constructing/spruce_lattice_fence_gate": {
    "criteria": {
      "has_minecraft:stick": "2025-11-21 22:28:43 +0000"
    },
    "done": true
  },
  "refurbished_furniture:recipes/misc/constructing/green_stool": {
    "criteria": {
      "has_planks": "2025-11-21 22:29:21 +0000"
    },
    "done": true
  },
  "refurbished_furniture:recipes/misc/constructing/oak_kitchen_sink": {
    "criteria": {
      "has_minecraft:oak_planks": "2025-11-21 22:29:21 +0000"
    },
    "done": true
  },
  "refurbished_furniture:recipes/misc/constructing/orange_stool": {
    "criteria": {
      "has_planks": "2025-11-21 22:29:21 +0000"
    },
    "done": true
  },
  "refurbished_furniture:recipes/misc/constructing/light_fridge": {
    "criteria": {
      "has_minecraft:iron_ingot": "2025-11-21 22:50:54 +0000"
    },
    "done": true
  },
  "minecraft:recipes/misc/iron_nugget_from_smelting": {
    "criteria": {
      "has_iron_leggings": "2025-11-21 22:50:51 +0000"
    },
    "done": true
  },
  "refurbished_furniture:recipes/misc/constructing/jungle_bath": {
    "criteria": {
      "has_minecraft:iron_ingot": "2025-11-21 22:50:54 +0000"
    },
    "done": true
  },
  "minecraft:recipes/food/baked_potato_from_campfire_cooking": {
    "criteria": {
      "has_potato": "2025-11-22 00:37:17 +0000"
    },
    "done": true
  },
  "refurbished_furniture:recipes/misc/constructing/yellow_lamp": {
    "criteria": {
      "has_planks": "2025-11-21 22:29:21 +0000"
    },
    "done": true
  },
  "waystones:recipes/decorations/magenta_sharestone": {
    "criteria": {
      "has_warp_stone": "2025-11-21 23:00:22 +0000"
    },
    "done": true
  },
  "farmersdelight:recipes/cooking/rabbit_stew": {
    "criteria": {
      "has_any_ingredient": "2025-11-21 23:43:47 +0000"
    },
    "done": true
  },
  "minecraft:recipes/redstone/birch_button": {
    "criteria": {
      "has_planks": "2025-11-21 22:29:27 +0000"
    },
    "done": true
  },
  "refurbished_furniture:recipes/misc/constructing/oak_kitchen_drawer": {
    "criteria": {
      "has_minecraft:oak_planks": "2025-11-21 22:29:21 +0000"
    },
    "done": true
  },
  "refurbished_furniture:recipes/misc/constructing/spruce_kitchen_cabinetry": {
    "criteria": {
      "has_minecraft:spruce_planks": "2025-11-21 22:51:02 +0000"
    },
    "done": true
  },
  "farmersdelight:recipes/cooking/stuffed_pumpkin_block": {
    "criteria": {
      "has_pumpkin": "2025-11-21 23:08:26 +0000"
    },
    "done": true
  },
  "minecraft:recipes/tools/golden_axe": {
    "criteria": {
      "has_gold_ingot": "2025-11-21 22:43:27 +0000"
    },
    "done": true
  },
  "waystones:recipes/decorations/warp_scroll": {
    "criteria": {
      "has_ender_pearl": "2025-11-21 22:52:44 +0000"
    },
    "done": true
  },
  "refurbished_furniture:recipes/misc/constructing/spruce_kitchen_sink": {
    "criteria": {
      "has_minecraft:spruce_planks": "2025-11-21 22:51:02 +0000"
    },
    "done": true
  },
  "refurbished_furniture:recipes/misc/constructing/dark_oak_toilet": {
    "criteria": {
      "has_minecraft:iron_ingot": "2025-11-21 22:50:54 +0000"
    },
    "done": true
  },
  "minecraft:recipes/combat/iron_chestplate": {
    "criteria": {
      "has_iron_ingot": "2025-11-21 22:50:54 +0000"
    },
    "done": true
  },
  "waystones:recipes/decorations/purple_portstone": {
    "criteria": {
      "has_warp_stone": "2025-11-21 23:00:22 +0000"
    },
    "done": true
  },
  "minecraft:recipes/decorations/oak_sign": {
    "criteria": {
      "has_planks": "2025-11-21 22:29:21 +0000"
    },
    "done": true
  },
  "minecraft:recipes/redstone/oak_trapdoor": {
    "criteria": {
      "has_planks": "2025-11-21 22:29:21 +0000"
    },
    "done": true
  },
  "refurbished_furniture:recipes/misc/constructing/cherry_bath": {
    "criteria": {
      "has_minecraft:iron_ingot": "2025-11-21 22:50:54 +0000"
    },
    "done": true
  },
  "moredelight:recipes/cooking/cooked_rice_with_beef": {
    "criteria": {
      "has_any_ingredient": "2025-11-21 23:48:45 +0000"
    },
    "done": true
  },
  "refurbished_furniture:recipes/misc/spatula": {
    "criteria": {
      "has_iron_ingot": "2025-11-21 22:50:54 +0000"
    },
    "done": true
  },
  "refurbished_furniture:recipes/misc/constructing/black_cooler": {
    "criteria": {
      "has_planks": "2025-11-21 22:29:21 +0000"
    },
    "done": true
  },
  "refurbished_furniture:recipes/misc/constructing/acacia_bath": {
    "criteria": {
      "has_minecraft:iron_ingot": "2025-11-21 22:50:54 +0000"
    },
    "done": true
  },
  "minecraft:recipes/tools/golden_pickaxe": {
    "criteria": {
      "has_gold_ingot": "2025-11-21 22:43:27 +0000"
    },
    "done": true
  },
  "refurbished_furniture:recipes/misc/constructing/lime_lamp": {
    "criteria": {
      "has_planks": "2025-11-21 22:29:21 +0000"
    },
    "done": true
  },
  "refurbished_furniture:recipes/misc/constructing/red_lamp": {
    "criteria": {
      "has_planks": "2025-11-21 22:29:21 +0000"
    },
    "done": true
  },
  "refurbished_furniture:recipes/misc/constructing/birch_cutting_board": {
    "criteria": {
      "has_minecraft:birch_planks": "2025-11-21 22:29:27 +0000"
    },
    "done": true
  },
  "refurbished_furniture:recipes/misc/dark_electricity_generator": {
    "criteria": {
      "has_iron_ingot": "2025-11-21 22:50:54 +0000"
    },
    "done": true
  },
  "minecraft:recipes/combat/stone_sword": {
    "criteria": {
      "has_cobblestone": "2025-11-21 22:31:38 +0000"
    },
    "done": true
  },
  "minecraft:recipes/decorations/cobblestone_wall": {
    "criteria": {
      "has_cobblestone": "2025-11-21 22:31:38 +0000"
    },
    "done": true
  },
  "refurbished_furniture:recipes/misc/constructing/crimson_storage_cabinet": {
    "criteria": {
      "has_minecraft:iron_ingot": "2025-11-21 22:50:54 +0000"
    },
    "done": true
  },
  "minecraft:recipes/food/cooked_cod_from_smoking": {
    "criteria": {
      "has_cod": "2025-11-22 01:13:47 +0000"
    },
    "done": true
  },
  "refurbished_furniture:recipes/misc/slicing/red_dye_from_sweet_berries": {
    "criteria": {
      "has_sweet_berries": "2025-11-21 23:01:06 +0000"
    },
    "done": true
  },
  "refurbished_furniture:recipes/misc/constructing/orange_lamp": {
    "criteria": {
      "has_planks": "2025-11-21 22:29:21 +0000"
    },
    "done": true
  },
  "minecraft:recipes/misc/gold_nugget_from_smelting": {
    "criteria": {
      "has_golden_helmet": "2025-11-22 01:37:15 +0000"
    },
    "done": true
  },
  "refurbished_furniture:recipes/misc/constructing/cherry_crate": {
    "criteria": {
      "has_minecraft:cherry_planks": "2025-11-22 02:10:07 +0000"
    },
    "done": true
  },
  "minecraft:recipes/tools/stone_axe": {
    "criteria": {
      "has_cobblestone": "2025-11-21 22:31:38 +0000"
    },
    "done": true
  },
  "moredelight:recipes/cooking/cooked_rice_with_porkchop": {
    "criteria": {
      "has_any_ingredient": "2025-11-21 23:48:45 +0000"
    },
    "done": true
  },
  "refurbished_furniture:recipes/misc/constructing/white_grill": {
    "criteria": {
      "has_minecraft:iron_ingot": "2025-11-21 22:50:54 +0000"
    },
    "done": true
  },
  "waystones:recipes/decorations/light_blue_sharestone": {
    "criteria": {
      "has_warp_stone": "2025-11-21 23:00:22 +0000"
    },
    "done": true
  },
  "refurbished_furniture:recipes/misc/constructing/dark_oak_basin": {
    "criteria": {
      "has_minecraft:iron_ingot": "2025-11-21 22:50:54 +0000"
    },
    "done": true
  },
  "refurbished_furniture:recipes/misc/constructing/dark_oak_lattice_fence_gate": {
    "criteria": {
      "has_minecraft:stick": "2025-11-21 22:28:43 +0000"
    },
    "done": true
  },
  "minecraft:recipes/misc/iron_nugget": {
    "criteria": {
      "has_iron_ingot": "2025-11-21 22:50:54 +0000"
    },
    "done": true
  },
  "refurbished_furniture:recipes/misc/constructing/pink_grill": {
    "criteria": {
      "has_minecraft:iron_ingot": "2025-11-21 22:50:54 +0000"
    },
    "done": true
  },
  "farmersdelight:recipes/cooking/mushroom_stew": {
    "criteria": {
      "has_any_ingredient": "2025-11-21 23:58:05 +0000"
    },
    "done": true
  },
  "minecraft:recipes/misc/white_dye": {
    "criteria": {
      "has_bone_meal": "2025-11-21 23:36:40 +0000"
    },
    "done": true
  },
  "farmersdelight:recipes/combat/flint_knife": {
    "criteria": {
      "has_stick": "2025-11-21 22:28:43 +0000"
    },
    "done": true
  },
  "minecraft:recipes/misc/gold_nugget": {
    "criteria": {
      "has_gold_ingot": "2025-11-21 22:43:27 +0000"
    },
    "done": true
  },
  "refurbished_furniture:recipes/misc/constructing/crimson_toilet": {
    "criteria": {
      "has_minecraft:iron_ingot": "2025-11-21 22:50:54 +0000"
    },
    "done": true
  },
  "minecraft:recipes/misc/bucket": {
    "criteria": {
      "has_iron_ingot": "2025-11-21 22:50:54 +0000"
    },
    "done": true
  },
  "refurbished_furniture:recipes/misc/constructing/cherry_basin": {
    "criteria": {
      "has_minecraft:iron_ingot": "2025-11-21 22:50:54 +0000"
    },
    "done": true
  },
  "waystones:recipes/decorations/light_gray_sharestone": {
    "criteria": {
      "has_warp_stone": "2025-11-21 23:00:22 +0000"
    },
    "done": true
  },
  "refurbished_furniture:recipes/misc/constructing/birch_kitchen_sink": {
    "criteria": {
      "has_minecraft:birch_planks": "2025-11-21 22:29:27 +0000"
    },
    "done": true
  },
  "vanillatweaks:dragon_drops": {
    "criteria": {
      "tick": "2025-11-21 22:15:48 +0000"
    },
    "done": true
  },
  "minecraft:recipes/combat/iron_helmet": {
    "criteria": {
      "has_iron_ingot": "2025-11-21 22:50:54 +0000"
    },
    "done": true
  },
  "minecraft:recipes/tools/golden_shovel": {
    "criteria": {
      "has_gold_ingot": "2025-11-21 22:43:27 +0000"
    },
    "done": true
  },
  "waystones:recipes/decorations/brown_portstone": {
    "criteria": {
      "has_warp_stone": "2025-11-21 23:00:22 +0000"
    },
    "done": true
  },
  "minecraft:story/mine_stone": {
    "criteria": {
      "get_stone": "2025-11-21 22:31:38 +0000"
    },
    "done": true
  },
  "minecraft:recipes/decorations/furnace": {
    "criteria": {
      "has_cobblestone": "2025-11-21 22:31:38 +0000"
    },
    "done": true
  },
  "minecraft:recipes/transportation/minecart": {
    "criteria": {
      "has_iron_ingot": "2025-11-21 22:50:54 +0000"
    },
    "done": true
  },
  "minecraft:recipes/food/beetroot_soup": {
    "criteria": {
      "has_beetroot": "2025-11-21 23:44:45 +0000"
    },
    "done": true
  },
  "minecraft:recipes/tools/iron_hoe": {
    "criteria": {
      "has_iron_ingot": "2025-11-21 22:50:54 +0000"
    },
    "done": true
  },
  "minecraft:recipes/food/golden_apple": {
    "criteria": {
      "has_gold_ingot": "2025-11-21 22:43:27 +0000"
    },
    "done": true
  },
  "farmersdelight:recipes/misc/iron_nugget_from_smelting_knife": {
    "criteria": {
      "has_iron_knife": "2025-11-22 00:38:53 +0000"
    },
    "done": true
  },
  "refurbished_furniture:recipes/misc/constructing/orange_trampoline": {
    "criteria": {
      "has_minecraft:iron_ingot": "2025-11-21 22:50:54 +0000"
    },
    "done": true
  },
  "minecraft:recipes/misc/bowl": {
    "criteria": {
      "has_brown_mushroom": "2025-11-21 23:58:05 +0000"
    },
    "done": true
  },
  "moredelight:recipes/cooking/diced_potatoes_with_chicken_cuts": {
    "criteria": {
      "has_any_ingredient": "2025-11-21 23:48:45 +0000"
    },
    "done": true
  },
  "refurbished_furniture:recipes/misc/constructing/computer": {
    "criteria": {
      "has_minecraft:iron_ingot": "2025-11-21 22:50:54 +0000"
    },
    "done": true
  },
  "refurbished_furniture:recipes/misc/constructing/light_toaster": {
    "criteria": {
      "has_minecraft:iron_ingot": "2025-11-21 22:50:54 +0000"
    },
    "done": true
  },
  "minecraft:recipes/food/baked_potato": {
    "criteria": {
      "has_potato": "2025-11-22 00:37:17 +0000"
    },
    "done": true
  },
  "refurbished_furniture:recipes/misc/constructing/cyan_trampoline": {
    "criteria": {
      "has_minecraft:iron_ingot": "2025-11-21 22:50:54 +0000"
    },
    "done": true
  },
  "enchantplus:list": {
    "criteria": {
      "requirement": "2025-11-22 00:43:50 +0000"
    },
    "done": true
  },
  "refurbished_furniture:recipes/misc/constructing/black_grill": {
    "criteria": {
      "has_minecraft:iron_ingot": "2025-11-21 22:50:54 +0000"
    },
    "done": true
  },
  "minecraft:recipes/redstone/birch_door": {
    "criteria": {
      "has_planks": "2025-11-21 22:29:27 +0000"
    },
    "done": true
  },
  "refurbished_furniture:recipes/misc/constructing/cherry_storage_cabinet": {
    "criteria": {
      "has_minecraft:iron_ingot": "2025-11-21 22:50:54 +0000"
    },
    "done": true
  },
  "minecraft:recipes/decorations/cherry_fence": {
    "criteria": {
      "has_planks": "2025-11-22 02:10:07 +0000"
    },
    "done": true
  },
  "minecraft:recipes/decorations/birch_fence": {
    "criteria": {
      "has_planks": "2025-11-21 22:29:27 +0000"
    },
    "done": true
  },
  "minecraft:recipes/combat/golden_boots": {
    "criteria": {
      "has_gold_ingot": "2025-11-21 22:43:27 +0000"
    },
    "done": true
  },
  "minecraft:recipes/tools/wooden_axe": {
    "criteria": {
      "has_stick": "2025-11-21 22:28:43 +0000"
    },
    "done": true
  },
  "minecraft:recipes/decorations/spruce_sign": {
    "criteria": {
      "has_planks": "2025-11-21 22:51:02 +0000"
    },
    "done": true
  },
  "refurbished_furniture:recipes/misc/constructing/magenta_cooler": {
    "criteria": {
      "has_planks": "2025-11-21 22:29:21 +0000"
    },
    "done": true
  },
  "minecraft:recipes/building_blocks/bricks": {
    "criteria": {
      "has_brick": "2025-11-22 00:47:07 +0000"
    },
    "done": true
  },
  "farmersdelight:recipes/cooking/noodle_soup": {
    "criteria": {
      "has_any_ingredient": "2025-11-22 01:13:23 +0000"
    },
    "done": true
  },
  "refurbished_furniture:recipes/misc/constructing/spruce_lattice_fence": {
    "criteria": {
      "has_minecraft:stick": "2025-11-21 22:28:43 +0000"
    },
    "done": true
  },
  "refurbished_furniture:recipes/misc/constructing/light_blue_cooler": {
    "criteria": {
      "has_planks": "2025-11-21 22:29:21 +0000"
    },
    "done": true
  },
  "refurbished_furniture:recipes/misc/constructing/spruce_kitchen_drawer": {
    "criteria": {
      "has_minecraft:spruce_planks": "2025-11-21 22:51:02 +0000"
    },
    "done": true
  },
  "refurbished_furniture:recipes/misc/constructing/dark_oak_storage_cabinet": {
    "criteria": {
      "has_minecraft:iron_ingot": "2025-11-21 22:50:54 +0000"
    },
    "done": true
  },
  "minecraft:recipes/misc/gold_nugget_from_blasting": {
    "criteria": {
      "has_golden_helmet": "2025-11-22 01:37:15 +0000"
    },
    "done": true
  },
  "refurbished_furniture:recipes/misc/constructing/white_lamp": {
    "criteria": {
      "has_planks": "2025-11-21 22:29:21 +0000"
    },
    "done": true
  },
  "farmersdelight:main/get_fd_seed": {
    "criteria": {
      "cabbage_seeds": "2025-11-21 23:44:09 +0000"
    },
    "done": true
  },
  "waystones:recipes/decorations/lime_sharestone": {
    "criteria": {
      "has_warp_stone": "2025-11-21 23:00:22 +0000"
    },
    "done": true
  },
  "refurbished_furniture:recipes/misc/constructing/cherry_drawer": {
    "criteria": {
      "has_minecraft:cherry_planks": "2025-11-22 02:10:07 +0000"
    },
    "done": true
  },
  "minecraft:recipes/misc/copper_nugget_from_blasting": {
    "criteria": {
      "has_copper_helmet": "2025-11-21 22:45:28 +0000"
    },
    "done": true
  },
  "refurbished_furniture:recipes/misc/constructing/cherry_mail_box": {
    "criteria": {
      "has_minecraft:cherry_planks": "2025-11-22 02:10:07 +0000"
    },
    "done": true
  },
  "minecraft:recipes/combat/golden_helmet": {
    "criteria": {
      "has_gold_ingot": "2025-11-21 22:43:27 +0000"
    },
    "done": true
  },
  "refurbished_furniture:recipes/misc/constructing/oak_mail_box": {
    "criteria": {
      "has_minecraft:oak_planks": "2025-11-21 22:29:21 +0000"
    },
    "done": true
  },
  "minecraft:recipes/food/cooked_salmon": {
    "criteria": {
      "has_salmon": "2025-11-21 22:40:32 +0000"
    },
    "done": true
  },
  "refurbished_furniture:recipes/misc/constructing/pink_sofa": {
    "criteria": {
      "has_planks": "2025-11-21 22:29:21 +0000"
    },
    "done": true
  },
  "minecraft:recipes/building_blocks/cherry_stairs": {
    "criteria": {
      "has_planks": "2025-11-22 02:10:07 +0000"
    },
    "done": true
  },
  "farmersdelight:recipes/cooking/chicken_soup": {
    "criteria": {
      "has_any_ingredient": "2025-11-21 23:43:47 +0000"
    },
    "done": true
  },
  "refurbished_furniture:recipes/misc/constructing/birch_chair": {
    "criteria": {
      "has_minecraft:birch_planks": "2025-11-21 22:29:27 +0000"
    },
    "done": true
  },
  "refurbished_furniture:recipes/misc/constructing/oak_bath": {
    "criteria": {
      "has_minecraft:oak_planks": "2025-11-21 22:29:21 +0000"
    },
    "done": true
  },
  "refurbished_furniture:recipes/misc/constructing/brown_lamp": {
    "criteria": {
      "has_planks": "2025-11-21 22:29:21 +0000"
    },
    "done": true
  },
  "refurbished_furniture:recipes/misc/constructing/yellow_sofa": {
    "criteria": {
      "has_planks": "2025-11-21 22:29:21 +0000"
    },
    "done": true
  },
  "vanillatweaks:multiplayer_sleep": {
    "criteria": {
      "tick": "2025-11-21 22:15:48 +0000"
    },
    "done": true
  },
  "farmersdelight:main/place_campfire": {
    "criteria": {
      "campfire": "2025-11-22 01:28:32 +0000"
    },
    "done": true
  },
  "refurbished_furniture:recipes/misc/constructing/pale_oak_lattice_fence_gate": {
    "criteria": {
      "has_minecraft:stick": "2025-11-21 22:28:43 +0000"
    },
    "done": true
  },
  "refurbished_furniture:recipes/misc/constructing/crimson_lattice_fence_gate": {
    "criteria": {
      "has_minecraft:stick": "2025-11-21 22:28:43 +0000"
    },
    "done": true
  },
  "farmersdelight:recipes/cooking/vegetable_noodles": {
    "criteria": {
      "has_any_ingredient": "2025-11-21 23:43:47 +0000"
    },
    "done": true
  },
  "refurbished_furniture:recipes/misc/constructing/red_grill": {
    "criteria": {
      "has_minecraft:iron_ingot": "2025-11-21 22:50:54 +0000"
    },
    "done": true
  },
  "minecraft:story/smelt_iron": {
    "criteria": {
      "iron": "2025-11-21 22:50:54 +0000"
    },
    "done": true
  },
  "refurbished_furniture:recipes/misc/constructing/orange_sofa": {
    "criteria": {
      "has_planks": "2025-11-21 22:29:21 +0000"
    },
    "done": true
  },
  "refurbished_furniture:recipes/misc/constructing/cherry_storage_jar": {
    "criteria": {
      "has_minecraft:cherry_planks": "2025-11-22 02:10:07 +0000"
    },
    "done": true
  },
  "minecraft:recipes/misc/pumpkin_seeds": {
    "criteria": {
      "has_pumpkin": "2025-11-21 23:08:26 +0000"
    },
    "done": true
  },
  "minecraft:recipes/decorations/crafting_table": {
    "criteria": {
      "unlock_right_away": "2025-11-21 22:15:48 +0000"
    },
    "done": true
  },
  "waystones:recipes/decorations/orange_sharestone": {
    "criteria": {
      "has_warp_stone": "2025-11-21 23:00:22 +0000"
    },
    "done": true
  },
  "minecraft:recipes/decorations/chest": {
    "criteria": {
      "has_lots_of_items": "2025-11-21 22:39:33 +0000"
    },
    "done": true
  },
  "waystones:recipes/decorations/black_portstone": {
    "criteria": {
      "has_warp_stone": "2025-11-21 23:00:22 +0000"
    },
    "done": true
  },
  "minecraft:recipes/tools/shears": {
    "criteria": {
      "has_iron_ingot": "2025-11-21 22:50:54 +0000"
    },
    "done": true
  },
  "minecraft:recipes/misc/stick": {
    "criteria": {
      "has_planks": "2025-11-21 22:29:21 +0000"
    },
    "done": true
  },
  "minecraft:recipes/building_blocks/emerald_block": {
    "criteria": {
      "has_emerald": "2025-11-21 23:00:18 +0000"
    },
    "done": true
  },
  "waystones:recipes/decorations/yellow_portstone": {
    "criteria": {
      "has_warp_stone": "2025-11-21 23:00:22 +0000"
    },
    "done": true
  },
  "farmersdelight:recipes/cooking/cabbage_rolls": {
    "criteria": {
      "has_any_ingredient": "2025-11-21 23:44:09 +0000"
    },
    "done": true
  },
  "refurbished_furniture:recipes/misc/constructing/lime_sofa": {
    "criteria": {
      "has_planks": "2025-11-21 22:29:21 +0000"
    },
    "done": true
  },
  "refurbished_furniture:recipes/misc/constructing/oak_crate": {
    "criteria": {
      "has_minecraft:oak_planks": "2025-11-21 22:29:21 +0000"
    },
    "done": true
  },
  "waystones:recipes/decorations/yellow_sharestone": {
    "criteria": {
      "has_warp_stone": "2025-11-21 23:00:22 +0000"
    },
    "done": true
  },
  "minecraft:adventure/sleep_in_bed": {
    "criteria": {
      "slept_in_bed": "2025-11-21 23:14:45 +0000"
    },
    "done": true
  },
  "refurbished_furniture:recipes/misc/constructing/spruce_kitchen_storage_cabinet": {
    "criteria": {
      "has_minecraft:spruce_planks": "2025-11-21 22:51:02 +0000"
    },
    "done": true
  },
  "minecraft:recipes/building_blocks/cobblestone_slab_from_cobblestone_stonecutting": {
    "criteria": {
      "has_cobblestone": "2025-11-21 22:31:38 +0000"
    },
    "done": true
  },
  "refurbished_furniture:recipes/misc/constructing/light_gray_trampoline": {
    "criteria": {
      "has_minecraft:iron_ingot": "2025-11-21 22:50:54 +0000"
    },
    "done": true
  },
  "refurbished_furniture:recipes/misc/constructing/birch_kitchen_drawer": {
    "criteria": {
      "has_minecraft:birch_planks": "2025-11-21 22:29:27 +0000"
    },
    "done": true
  },
  "minecraft:recipes/building_blocks/oak_stairs": {
    "criteria": {
      "has_planks": "2025-11-21 22:29:21 +0000"
    },
    "done": true
  },
  "minecraft:recipes/decorations/birch_sign": {
    "criteria": {
      "has_planks": "2025-11-21 22:29:27 +0000"
    },
    "done": true
  },
  "minecraft:recipes/transportation/cherry_boat": {
    "criteria": {
      "in_water": "2025-11-21 22:26:17 +0000"
    },
    "done": true
  },
  "refurbished_furniture:recipes/misc/constructing/mangrove_basin": {
    "criteria": {
      "has_minecraft:iron_ingot": "2025-11-21 22:50:54 +0000"
    },
    "done": true
  },
  "refurbished_furniture:recipes/misc/constructing/gray_grill": {
    "criteria": {
      "has_minecraft:iron_ingot": "2025-11-21 22:50:54 +0000"
    },
    "done": true
  },
  "refurbished_furniture:recipes/misc/constructing/red_cooler": {
    "criteria": {
      "has_planks": "2025-11-21 22:29:21 +0000"
    },
    "done": true
  },
  "minecraft:adventure/kill_all_mobs": {
    "criteria": {
      "minecraft:zombie": "2025-11-21 22:25:38 +0000"
    },
    "done": false
  },
  "minecraft:recipes/building_blocks/birch_wood": {
    "criteria": {
      "has_log": "2025-11-21 22:27:15 +0000"
    },
    "done": true
  },
  "refurbished_furniture:recipes/misc/constructing/birch_bath": {
    "criteria": {
      "has_minecraft:birch_planks": "2025-11-21 22:29:27 +0000"
    },
    "done": true
  },
  "refurbished_furniture:recipes/misc/constructing/green_trampoline": {
    "criteria": {
      "has_minecraft:iron_ingot": "2025-11-21 22:50:54 +0000"
    },
    "done": true
  },
  "minecraft:recipes/redstone/cherry_trapdoor": {
    "criteria": {
      "has_planks": "2025-11-22 02:10:07 +0000"
    },
    "done": true
  },
  "refurbished_furniture:recipes/misc/constructing/oak_light_ceiling_fan": {
    "criteria": {
      "has_minecraft:oak_planks": "2025-11-21 22:29:21 +0000"
    },
    "done": true
  },
  "refurbished_furniture:recipes/misc/constructing/brown_trampoline": {
    "criteria": {
      "has_minecraft:iron_ingot": "2025-11-21 22:50:54 +0000"
    },
    "done": true
  },
  "farmersdelight:recipes/food/cabbage_from_leaves": {
    "criteria": {
      "has_cabbage_leaf": "2025-11-22 01:41:49 +0000"
    },
    "done": true
  },
  "minecraft:recipes/decorations/oak_fence": {
    "criteria": {
      "has_planks": "2025-11-21 22:29:21 +0000"
    },
    "done": true
  },
  "refurbished_furniture:recipes/misc/constructing/spruce_bath": {
    "criteria": {
      "has_minecraft:iron_ingot": "2025-11-21 22:50:54 +0000"
    },
    "done": true
  },
  "minecraft:recipes/redstone/cherry_button": {
    "criteria": {
      "has_planks": "2025-11-22 02:10:07 +0000"
    },
    "done": true
  },
  "minecraft:recipes/building_blocks/cherry_planks": {
    "criteria": {
      "has_log": "2025-11-21 22:54:12 +0000"
    },
    "done": true
  },
  "minecraft:recipes/food/cooked_porkchop_from_campfire_cooking": {
    "criteria": {
      "has_porkchop": "2025-11-22 01:13:23 +0000"
    },
    "done": true
  },
  "refurbished_furniture:recipes/misc/constructing/crimson_light_ceiling_fan": {
    "criteria": {
      "has_minecraft:iron_ingot": "2025-11-21 22:50:54 +0000"
    },
    "done": true
  },
  "refurbished_furniture:recipes/misc/constructing/oak_basin": {
    "criteria": {
      "has_minecraft:oak_planks": "2025-11-21 22:29:21 +0000"
    },
    "done": true
  },
  "farmersdelight:recipes/cooking/pumpkin_soup": {
    "criteria": {
      "has_any_ingredient": "2025-11-21 23:08:26 +0000"
    },
    "done": true
  },
  "minecraft:recipes/combat/golden_chestplate": {
    "criteria": {
      "has_gold_ingot": "2025-11-21 22:43:27 +0000"
    },
    "done": true
  },
  "waystones:recipes/decorations/lime_portstone": {
    "criteria": {
      "has_warp_stone": "2025-11-21 23:00:22 +0000"
    },
    "done": true
  },
  "refurbished_furniture:recipes/misc/constructing/lime_trampoline": {
    "criteria": {
      "has_minecraft:iron_ingot": "2025-11-21 22:50:54 +0000"
    },
    "done": true
  },
  "minecraft:recipes/building_blocks/iron_block": {
    "criteria": {
      "has_iron_ingot": "2025-11-21 22:50:54 +0000"
    },
    "done": true
  },
  "waystones:recipes/decorations/blue_portstone": {
    "criteria": {
      "has_warp_stone": "2025-11-21 23:00:22 +0000"
    },
    "done": true
  },
  "minecraft:recipes/misc/red_dye_from_poppy": {
    "criteria": {
      "has_poppy": "2025-11-21 23:15:54 +0000"
    },
    "done": true
  },
  "minecraft:recipes/building_blocks/spruce_wood": {
    "criteria": {
      "has_log": "2025-11-21 23:04:14 +0000"
    },
    "done": true
  },
  "minecraft:recipes/building_blocks/clay": {
    "criteria": {
      "has_clay_ball": "2025-11-22 00:43:20 +0000"
    },
    "done": true
  },
  "refurbished_furniture:recipes/misc/constructing/birch_storage_cabinet": {
    "criteria": {
      "has_minecraft:birch_planks": "2025-11-21 22:29:27 +0000"
    },
    "done": true
  },
  "refurbished_furniture:recipes/misc/constructing/light_microwave": {
    "criteria": {
      "has_minecraft:iron_ingot": "2025-11-21 22:50:54 +0000"
    },
    "done": true
  },
  "refurbished_furniture:recipes/misc/constructing/cyan_grill": {
    "criteria": {
      "has_minecraft:iron_ingot": "2025-11-21 22:50:54 +0000"
    },
    "done": true
  },
  "refurbished_furniture:recipes/misc/constructing/dark_oak_bath": {
    "criteria": {
      "has_minecraft:iron_ingot": "2025-11-21 22:50:54 +0000"
    },
    "done": true
  },
  "minecraft:recipes/redstone/birch_fence_gate": {
    "criteria": {
      "has_planks": "2025-11-21 22:29:27 +0000"
    },
    "done": true
  },
  "farmersdelight:recipes/decorations/cooking_pot": {
    "criteria": {
      "has_iron_ingot": "2025-11-21 22:50:54 +0000"
    },
    "done": true
  },
  "waystones:recipes/decorations/white_portstone": {
    "criteria": {
      "has_warp_stone": "2025-11-21 23:00:22 +0000"
    },
    "done": true
  },
  "refurbished_furniture:recipes/misc/constructing/oak_lattice_fence_gate": {
    "criteria": {
      "has_minecraft:stick": "2025-11-21 22:28:43 +0000"
    },
    "done": true
  },
  "minecraft:recipes/building_blocks/stone": {
    "criteria": {
      "has_cobblestone": "2025-11-21 22:31:38 +0000"
    },
    "done": true
  },
  "refurbished_furniture:recipes/misc/constructing/birch_toilet": {
    "criteria": {
      "has_minecraft:birch_planks": "2025-11-21 22:29:27 +0000"
    },
    "done": true
  },
  "farmersdelight:recipes/food/barbecue_stick": {
    "criteria": {
      "has_tomato": "2025-11-21 22:39:33 +0000"
    },
    "done": true
  },
  "minecraft:recipes/transportation/bamboo_raft": {
    "criteria": {
      "in_water": "2025-11-21 22:26:17 +0000"
    },
    "done": true
  },
  "refurbished_furniture:recipes/misc/constructing/acacia_light_ceiling_fan": {
    "criteria": {
      "has_minecraft:iron_ingot": "2025-11-21 22:50:54 +0000"
    },
    "done": true
  },
  "refurbished_furniture:recipes/misc/constructing/light_blue_trampoline": {
    "criteria": {
      "has_minecraft:iron_ingot": "2025-11-21 22:50:54 +0000"
    },
    "done": true
  },
  "minecraft:recipes/decorations/smithing_table": {
    "criteria": {
      "has_iron_ingot": "2025-11-21 22:50:54 +0000"
    },
    "done": true
  },
  "refurbished_furniture:recipes/misc/constructing/spruce_storage_jar": {
    "criteria": {
      "has_minecraft:spruce_planks": "2025-11-21 22:51:02 +0000"
    },
    "done": true
  },
  "universal_shops:recipe/tradeshop_group/trade_block": {
    "criteria": {
      "item_required2": "2025-11-21 22:28:43 +0000"
    },
    "done": true
  },
  "refurbished_furniture:recipes/misc/constructing/crimson_basin": {
    "criteria": {
      "has_minecraft:iron_ingot": "2025-11-21 22:50:54 +0000"
    },
    "done": true
  },
  "refurbished_furniture:recipes/misc/constructing/crimson_bath": {
    "criteria": {
      "has_minecraft:iron_ingot": "2025-11-21 22:50:54 +0000"
    },
    "done": true
  },
  "refurbished_furniture:recipes/misc/constructing/black_trampoline": {
    "criteria": {
      "has_minecraft:iron_ingot": "2025-11-21 22:50:54 +0000"
    },
    "done": true
  },
  "refurbished_furniture:recipes/misc/constructing/magenta_stool": {
    "criteria": {
      "has_planks": "2025-11-21 22:29:21 +0000"
    },
    "done": true
  },
  "moredelight:recipes/cooking/diced_potatoes_with_egg_and_tomato": {
    "criteria": {
      "has_any_ingredient": "2025-11-21 22:39:33 +0000"
    },
    "done": true
  },
  "farmersdelight:recipes/cooking/baked_cod_stew": {
    "criteria": {
      "has_any_ingredient": "2025-11-21 22:39:33 +0000"
    },
    "done": true
  },
  "farmersdelight:recipes/combat/golden_knife": {
    "criteria": {
      "has_gold_ingot": "2025-11-21 22:43:27 +0000"
    },
    "done": true
  },
  "refurbished_furniture:recipes/misc/constructing/light_stove": {
    "criteria": {
      "has_minecraft:iron_ingot": "2025-11-21 22:50:54 +0000"
    },
    "done": true
  },
  "minecraft:recipes/food/bread": {
    "criteria": {
      "has_wheat": "2025-11-21 23:06:14 +0000"
    },
    "done": true
  },
  "refurbished_furniture:recipes/misc/constructing/oak_drawer": {
    "criteria": {
      "has_minecraft:oak_planks": "2025-11-21 22:29:21 +0000"
    },
    "done": true
  },
  "minecraft:recipes/transportation/spruce_boat": {
    "criteria": {
      "in_water": "2025-11-21 22:26:17 +0000"
    },
    "done": true
  },
  "refurbished_furniture:recipes/misc/constructing/green_cooler": {
    "criteria": {
      "has_planks": "2025-11-21 22:29:21 +0000"
    },
    "done": true
  },
  "moredelight:recipes/food/chicken_salad": {
    "criteria": {
      "has_bowl": "2025-11-22 01:27:00 +0000"
    },
    "done": true
  },
  "minecraft:recipes/building_blocks/birch_slab": {
    "criteria": {
      "has_planks": "2025-11-21 22:29:27 +0000"
    },
    "done": true
  },
  "refurbished_furniture:recipes/misc/knife": {
    "criteria": {
      "has_iron_ingot": "2025-11-21 22:50:54 +0000"
    },
    "done": true
  },
  "refurbished_furniture:recipes/misc/workbench": {
    "criteria": {
      "has_planks": "2025-11-21 22:29:21 +0000"
    },
    "done": true
  },
  "refurbished_furniture:recipes/misc/constructing/pale_oak_bath": {
    "criteria": {
      "has_minecraft:iron_ingot": "2025-11-21 22:50:54 +0000"
    },
    "done": true
  },
  "minecraft:recipes/building_blocks/hay_block": {
    "criteria": {
      "has_wheat": "2025-11-21 23:06:14 +0000"
    },
    "done": true
  },
  "refurbished_furniture:recipes/misc/constructing/birch_lattice_fence": {
    "criteria": {
      "has_minecraft:stick": "2025-11-21 22:28:43 +0000"
    },
    "done": true
  },
  "refurbished_furniture:recipes/misc/constructing/brown_sofa": {
    "criteria": {
      "has_planks": "2025-11-21 22:29:21 +0000"
    },
    "done": true
  },
  "refurbished_furniture:recipes/misc/constructing/door_mat": {
    "criteria": {
      "has_minecraft:wheat": "2025-11-21 23:06:14 +0000"
    },
    "done": true
  },
  "refurbished_furniture:recipes/misc/constructing/spruce_light_ceiling_fan": {
    "criteria": {
      "has_minecraft:iron_ingot": "2025-11-21 22:50:54 +0000"
    },
    "done": true
  },
  "minecraft:husbandry/root": {
    "criteria": {
      "consumed_item": "2025-11-21 22:39:56 +0000"
    },
    "done": true
  },
  "waystones:recipes/decorations/warp_stone": {
    "criteria": {
      "has_ender_pearl": "2025-11-21 22:52:44 +0000"
    },
    "done": true
  },
  "minecraft:recipes/transportation/birch_boat": {
    "criteria": {
      "in_water": "2025-11-21 22:26:17 +0000"
    },
    "done": true
  },
  "refurbished_furniture:recipes/misc/constructing/pale_oak_toilet": {
    "criteria": {
      "has_minecraft:iron_ingot": "2025-11-21 22:50:54 +0000"
    },
    "done": true
  },
  "refurbished_furniture:recipes/misc/constructing/light_blue_lamp": {
    "criteria": {
      "has_planks": "2025-11-21 22:29:21 +0000"
    },
    "done": true
  },
  "minecraft:recipes/building_blocks/cherry_wood": {
    "criteria": {
      "has_log": "2025-11-21 22:54:12 +0000"
    },
    "done": true
  },
  "minecraft:recipes/decorations/spruce_fence": {
    "criteria": {
      "has_planks": "2025-11-21 22:51:02 +0000"
    },
    "done": true
  },
  "farmersdelight:recipes/cooking/squid_ink_pasta": {
    "criteria": {
      "has_any_ingredient": "2025-11-21 22:39:33 +0000"
    },
    "done": true
  },
  "refurbished_furniture:recipes/misc/constructing/blue_sofa": {
    "criteria": {
      "has_planks": "2025-11-21 22:29:21 +0000"
    },
    "done": true
  },
  "refurbished_furniture:recipes/misc/constructing/warped_basin": {
    "criteria": {
      "has_minecraft:iron_ingot": "2025-11-21 22:50:54 +0000"
    },
    "done": true
  },
  "farmersdelight:recipes/decorations/skillet": {
    "criteria": {
      "has_brick": "2025-11-22 00:47:07 +0000"
    },
    "done": true
  },
  "minecraft:recipes/transportation/oak_boat": {
    "criteria": {
      "in_water": "2025-11-21 22:26:17 +0000"
    },
    "done": true
  },
  "refurbished_furniture:recipes/misc/constructing/doorbell": {
    "criteria": {
      "has_minecraft:gold_ingot": "2025-11-21 22:43:27 +0000"
    },
    "done": true
  },
  "farmersdelight:main/plant_all_crops": {
    "criteria": {
      "cabbage": "2025-11-21 23:50:05 +0000",
      "onion": "2025-11-21 23:49:12 +0000",
      "potato": "2025-11-22 00:37:18 +0000",
      "red_mushroom": "2025-11-21 23:59:21 +0000",
      "wheat": "2025-11-21 23:06:25 +0000",
      "pumpkin": "2025-11-21 23:27:49 +0000",
      "beetroot": "2025-11-21 23:50:36 +0000",
      "brown_mushroom": "2025-11-21 23:59:16 +0000",
      "carrot": "2025-11-21 23:43:49 +0000"
    },
    "done": false
  },
  "refurbished_furniture:recipes/misc/constructing/light_lightswitch": {
    "criteria": {
      "has_minecraft:iron_ingot": "2025-11-21 22:50:54 +0000"
    },
    "done": true
  },
  "minecraft:recipes/misc/paper": {
    "criteria": {
      "has_reeds": "2025-11-22 01:14:38 +0000"
    },
    "done": true
  },
  "refurbished_furniture:recipes/misc/constructing/brown_cooler": {
    "criteria": {
      "has_planks": "2025-11-21 22:29:21 +0000"
    },
    "done": true
  },
  "refurbished_furniture:recipes/misc/constructing/light_blue_stool": {
    "criteria": {
      "has_planks": "2025-11-21 22:29:21 +0000"
    },
    "done": true
  },
  "farmersdelight:recipes/cooking/cooked_rice": {
    "criteria": {
      "has_rice": "2025-11-22 00:40:17 +0000"
    },
    "done": true
  },
  "minecraft:recipes/building_blocks/coal_block": {
    "criteria": {
      "has_coal": "2025-11-21 22:31:39 +0000"
    },
    "done": true
  },
  "minecraft:recipes/redstone/light_weighted_pressure_plate": {
    "criteria": {
      "has_gold_ingot": "2025-11-21 22:43:27 +0000"
    },
    "done": true
  },
  "refurbished_furniture:recipes/misc/constructing/cherry_lattice_fence": {
    "criteria": {
      "has_minecraft:stick": "2025-11-21 22:28:43 +0000"
    },
    "done": true
  },
  "waystones:recipes/decorations/end_stone_waystone": {
    "criteria": {
      "has_warp_stone": "2025-11-21 23:00:22 +0000"
    },
    "done": true
  },
  "minecraft:recipes/building_blocks/spruce_slab": {
    "criteria": {
      "has_planks": "2025-11-21 22:51:02 +0000"
    },
    "done": true
  },
  "farmersdelight:recipes/cooking/fried_rice": {
    "criteria": {
      "has_any_ingredient": "2025-11-21 23:43:47 +0000"
    },
    "done": true
  },
  "refurbished_furniture:recipes/misc/constructing/mangrove_toilet": {
    "criteria": {
      "has_minecraft:iron_ingot": "2025-11-21 22:50:54 +0000"
    },
    "done": true
  },
  "refurbished_furniture:recipes/misc/constructing/purple_cooler": {
    "criteria": {
      "has_planks": "2025-11-21 22:29:21 +0000"
    },
    "done": true
  },
  "refurbished_furniture:recipes/misc/constructing/warped_storage_cabinet": {
    "criteria": {
      "has_minecraft:iron_ingot": "2025-11-21 22:50:54 +0000"
    },
    "done": true
  },
  "refurbished_furniture:recipes/misc/constructing/red_trampoline": {
    "criteria": {
      "has_minecraft:iron_ingot": "2025-11-21 22:50:54 +0000"
    },
    "done": true
  },
  "refurbished_furniture:recipes/misc/constructing/cyan_cooler": {
    "criteria": {
      "has_planks": "2025-11-21 22:29:21 +0000"
    },
    "done": true
  },
  "minecraft:recipes/decorations/lodestone": {
    "criteria": {
      "has_iron_ingot": "2025-11-21 22:50:54 +0000"
    },
    "done": true
  },
  "refurbished_furniture:recipes/misc/constructing/oak_chair": {
    "criteria": {
      "has_minecraft:oak_planks": "2025-11-21 22:29:21 +0000"
    },
    "done": true
  },
  "minecraft:recipes/redstone/oak_button": {
    "criteria": {
      "has_planks": "2025-11-21 22:29:21 +0000"
    },
    "done": true
  },
  "waystones:recipes/decorations/red_sharestone": {
    "criteria": {
      "has_warp_stone": "2025-11-21 23:00:22 +0000"
    },
    "done": true
  },
  "refurbished_furniture:recipes/misc/constructing/light_gray_cooler": {
    "criteria": {
      "has_planks": "2025-11-21 22:29:21 +0000"
    },
    "done": true
  },
  "refurbished_furniture:recipes/misc/constructing/white_cooler": {
    "criteria": {
      "has_planks": "2025-11-21 22:29:21 +0000"
    },
    "done": true
  },
  "waystones:recipes/decorations/cyan_sharestone": {
    "criteria": {
      "has_warp_stone": "2025-11-21 23:00:22 +0000"
    },
    "done": true
  },
  "minecraft:recipes/decorations/decorated_pot_simple": {
    "criteria": {
      "has_brick": "2025-11-22 00:47:07 +0000"
    },
    "done": true
  },
  "minecraft:recipes/building_blocks/birch_stairs": {
    "criteria": {
      "has_planks": "2025-11-21 22:29:27 +0000"
    },
    "done": true
  },
  "refurbished_furniture:recipes/misc/constructing/red_sofa": {
    "criteria": {
      "has_planks": "2025-11-21 22:29:21 +0000"
    },
    "done": true
  },
  "minecraft:recipes/food/pumpkin_pie": {
    "criteria": {
      "has_pumpkin": "2025-11-21 23:08:26 +0000"
    },
    "done": true
  },
  "refurbished_furniture:recipes/misc/constructing/spruce_cutting_board": {
    "criteria": {
      "has_minecraft:spruce_planks": "2025-11-21 22:51:02 +0000"
    },
    "done": true
  },
  "cookingforblockheads:recipes/decorations/sink": {
    "criteria": {
      "has_water_bucket": "2025-11-21 23:23:44 +0000"
    },
    "done": true
  },
  "minecraft:husbandry/complete_catalogue": {
    "criteria": {
      "minecraft:siamese": "2025-11-22 01:19:51 +0000"
    },
    "done": false
  },
  "refurbished_furniture:recipes/misc/constructing/blue_trampoline": {
    "criteria": {
      "has_minecraft:iron_ingot": "2025-11-21 22:50:54 +0000"
    },
    "done": true
  },
  "waystones:recipes/decorations/purple_sharestone": {
    "criteria": {
      "has_warp_stone": "2025-11-21 23:00:22 +0000"
    },
    "done": true
  },
  "moredelight:combat/wooden_knife": {
    "criteria": {
      "has_wood": "2025-11-21 22:28:43 +0000"
    },
    "done": true
  },
  "refurbished_furniture:recipes/food/dough": {
    "criteria": {
      "has_water": "2025-11-21 23:23:44 +0000"
    },
    "done": true
  },
  "refurbished_furniture:recipes/misc/constructing/warped_light_ceiling_fan": {
    "criteria": {
      "has_minecraft:iron_ingot": "2025-11-21 22:50:54 +0000"
    },
    "done": true
  },
  "waystones:recipes/decorations/deepslate_waystone": {
    "criteria": {
      "has_warp_stone": "2025-11-21 23:00:22 +0000"
    },
    "done": true
  },
  "moredelight:recipes/food/tomato_sandwich": {
    "criteria": {
      "has_tomato": "2025-11-21 22:39:33 +0000"
    },
    "done": true
  },
  "minecraft:recipes/combat/iron_sword": {
    "criteria": {
      "has_iron_ingot": "2025-11-21 22:50:54 +0000"
    },
    "done": true
  },
  "minecraft:recipes/tools/iron_pickaxe": {
    "criteria": {
      "has_iron_ingot": "2025-11-21 22:50:54 +0000"
    },
    "done": true
  },
  "refurbished_furniture:recipes/misc/constructing/blue_lamp": {
    "criteria": {
      "has_planks": "2025-11-21 22:29:21 +0000"
    },
    "done": true
  },
  "enchantplus:weapons/sword/base": {
    "criteria": {
      "xp_boost": "2025-11-22 01:06:09 +0000"
    },
    "done": false
  },
  "refurbished_furniture:recipes/misc/constructing/spruce_toilet": {
    "criteria": {
      "has_minecraft:iron_ingot": "2025-11-21 22:50:54 +0000"
    },
    "done": true
  },
  "refurbished_furniture:recipes/misc/constructing/red_stool": {
    "criteria": {
      "has_planks": "2025-11-21 22:29:21 +0000"
    },
    "done": true
  },
  "minecraft:recipes/transportation/mangrove_boat": {
    "criteria": {
      "in_water": "2025-11-21 22:26:17 +0000"
    },
    "done": true
  },
  "minecraft:recipes/redstone/spruce_button": {
    "criteria": {
      "has_planks": "2025-11-21 22:51:02 +0000"
    },
    "done": true
  },
  "minecraft:recipes/decorations/torch": {
    "criteria": {
      "has_stone_pickaxe": "2025-11-21 23:16:57 +0000"
    },
    "done": true
  },
  "waystones:recipes/decorations/cyan_portstone": {
    "criteria": {
      "has_warp_stone": "2025-11-21 23:00:22 +0000"
    },
    "done": true
  },
  "moredelight:combat/stone_knife": {
    "criteria": {
      "has_stone": "2025-11-21 22:31:38 +0000"
    },
    "done": true
  },
  "minecraft:recipes/combat/shield": {
    "criteria": {
      "has_iron_ingot": "2025-11-21 22:50:54 +0000"
    },
    "done": true
  },
  "waystones:recipes/decorations/gray_sharestone": {
    "criteria": {
      "has_warp_stone": "2025-11-21 23:00:22 +0000"
    },
    "done": true
  },
  "refurbished_furniture:recipes/misc/wrench": {
    "criteria": {
      "has_iron_ingot": "2025-11-21 22:50:54 +0000"
    },
    "done": true
  },
  "minecraft:recipes/redstone/hopper": {
    "criteria": {
      "has_iron_ingot": "2025-11-21 22:50:54 +0000"
    },
    "done": true
  },
  "refurbished_furniture:recipes/misc/constructing/spruce_mail_box": {
    "criteria": {
      "has_minecraft:spruce_planks": "2025-11-21 22:51:02 +0000"
    },
    "done": true
  },
  "waystones:recipes/decorations/green_sharestone": {
    "criteria": {
      "has_warp_stone": "2025-11-21 23:00:22 +0000"
    },
    "done": true
  },
  "waystones:recipes/decorations/brown_sharestone": {
    "criteria": {
      "has_warp_stone": "2025-11-21 23:00:22 +0000"
    },
    "done": true
  },
  "minecraft:recipes/misc/gold_ingot_from_smelting_raw_gold": {
    "criteria": {
      "has_the_recipe": "2025-11-21 22:43:27 +0000"
    },
    "done": true
  },
  "minecraft:recipes/decorations/iron_bars": {
    "criteria": {
      "has_iron_ingot": "2025-11-21 22:50:54 +0000"
    },
    "done": true
  },
  "refurbished_furniture:recipes/misc/constructing/cherry_kitchen_cabinetry": {
    "criteria": {
      "has_minecraft:cherry_planks": "2025-11-22 02:10:07 +0000"
    },
    "done": true
  },
  "minecraft:recipes/building_blocks/spruce_planks": {
    "criteria": {
      "has_logs": "2025-11-21 23:04:14 +0000"
    },
    "done": true
  },
  "refurbished_furniture:recipes/misc/constructing/lime_stool": {
    "criteria": {
      "has_planks": "2025-11-21 22:29:21 +0000"
    },
    "done": true
  },
  "refurbished_furniture:recipes/misc/constructing/warped_bath": {
    "criteria": {
      "has_minecraft:iron_ingot": "2025-11-21 22:50:54 +0000"
    },
    "done": true
  },
  "refurbished_furniture:recipes/misc/constructing/green_grill": {
    "criteria": {
      "has_minecraft:iron_ingot": "2025-11-21 22:50:54 +0000"
    },
    "done": true
  },
  "refurbished_furniture:recipes/misc/constructing/brown_grill": {
    "criteria": {
      "has_minecraft:iron_ingot": "2025-11-21 22:50:54 +0000"
    },
    "done": true
  },
  "farmersdelight:recipes/decorations/spruce_cabinet": {
    "criteria": {
      "has_spruce_trapdoor": "2025-11-21 23:22:30 +0000"
    },
    "done": true
  },
  "refurbished_furniture:recipes/misc/constructing/acacia_basin": {
    "criteria": {
      "has_minecraft:iron_ingot": "2025-11-21 22:50:54 +0000"
    },
    "done": true
  },
  "refurbished_furniture:recipes/misc/constructing/magenta_lamp": {
    "criteria": {
      "has_planks": "2025-11-21 22:29:21 +0000"
    },
    "done": true
  },
  "refurbished_furniture:recipes/misc/constructing/cherry_table": {
    "criteria": {
      "has_minecraft:cherry_planks": "2025-11-22 02:10:07 +0000"
    },
    "done": true
  },
  "minecraft:recipes/food/cooked_porkchop": {
    "criteria": {
      "has_porkchop": "2025-11-22 01:13:23 +0000"
    },
    "done": true
  },
  "minecraft:recipes/building_blocks/oak_slab": {
    "criteria": {
      "has_planks": "2025-11-21 22:29:21 +0000"
    },
    "done": true
  },
  "minecraft:husbandry/tame_an_animal": {
    "criteria": {
      "tamed_animal": "2025-11-22 01:19:51 +0000"
    },
    "done": true
  },
  "farmersdelight:recipes/food/roasted_mutton_chops": {
    "criteria": {
      "has_mutton": "2025-11-22 01:57:23 +0000"
    },
    "done": true
  },
  "refurbished_furniture:recipes/misc/constructing/purple_grill": {
    "criteria": {
      "has_minecraft:iron_ingot": "2025-11-21 22:50:54 +0000"
    },
    "done": true
  },
  "refurbished_furniture:recipes/misc/constructing/television": {
    "criteria": {
      "has_minecraft:iron_ingot": "2025-11-21 22:50:54 +0000"
    },
    "done": true
  },
  "minecraft:recipes/food/cooked_salmon_from_smoking": {
    "criteria": {
      "has_salmon": "2025-11-21 22:40:32 +0000"
    },
    "done": true
  },
  "refurbished_furniture:recipes/misc/constructing/cherry_desk": {
    "criteria": {
      "has_minecraft:cherry_planks": "2025-11-22 02:10:07 +0000"
    },
    "done": true
  },
  "refurbished_furniture:recipes/misc/constructing/gray_lamp": {
    "criteria": {
      "has_planks": "2025-11-21 22:29:21 +0000"
    },
    "done": true
  },
  "farmersdelight:recipes/building_blocks/tomato_crate": {
    "criteria": {
      "has_tomato": "2025-11-21 22:39:33 +0000"
    },
    "done": true
  },
  "refurbished_furniture:recipes/misc/constructing/warped_lattice_fence_gate": {
    "criteria": {
      "has_minecraft:stick": "2025-11-21 22:28:43 +0000"
    },
    "done": true
  },
  "moredelight:recipes/cooking/diced_potatoes_with_beef": {
    "criteria": {
      "has_any_ingredient": "2025-11-21 23:48:45 +0000"
    },
    "done": true
  },
  "refurbished_furniture:recipes/misc/constructing/acacia_storage_cabinet": {
    "criteria": {
      "has_minecraft:iron_ingot": "2025-11-21 22:50:54 +0000"
    },
    "done": true
  },
  "minecraft:recipes/redstone/cherry_fence_gate": {
    "criteria": {
      "has_planks": "2025-11-22 02:10:07 +0000"
    },
    "done": true
  },
  "waystones:recipes/decorations/red_portstone": {
    "criteria": {
      "has_warp_stone": "2025-11-21 23:00:22 +0000"
    },
    "done": true
  },
  "refurbished_furniture:recipes/misc/constructing/spruce_basin": {
    "criteria": {
      "has_minecraft:iron_ingot": "2025-11-21 22:50:54 +0000"
    },
    "done": true
  },
  "farmersdelight:recipes/decorations/stove": {
    "criteria": {
      "has_campfire": "2025-11-22 01:28:15 +0000"
    },
    "done": true
  },
  "refurbished_furniture:recipes/misc/constructing/jungle_basin": {
    "criteria": {
      "has_minecraft:iron_ingot": "2025-11-21 22:50:54 +0000"
    },
    "done": true
  },
  "minecraft:recipes/combat/iron_boots": {
    "criteria": {
      "has_iron_ingot": "2025-11-21 22:50:54 +0000"
    },
    "done": true
  },
  "minecraft:recipes/building_blocks/birch_planks": {
    "criteria": {
      "has_logs": "2025-11-21 22:27:15 +0000"
    },
    "done": true
  },
  "minecraft:recipes/redstone/spruce_pressure_plate": {
    "criteria": {
      "has_planks": "2025-11-21 22:51:02 +0000"
    },
    "done": true
  },
  "refurbished_furniture:recipes/misc/constructing/light_blue_sofa": {
    "criteria": {
      "has_planks": "2025-11-21 22:29:21 +0000"
    },
    "done": true
  },
  "waystones:recipes/decorations/gray_portstone": {
    "criteria": {
      "has_warp_stone": "2025-11-21 23:00:22 +0000"
    },
    "done": true
  },
  "refurbished_furniture:recipes/misc/constructing/pink_trampoline": {
    "criteria": {
      "has_minecraft:iron_ingot": "2025-11-21 22:50:54 +0000"
    },
    "done": true
  },
  "refurbished_furniture:recipes/misc/constructing/birch_drawer": {
    "criteria": {
      "has_minecraft:birch_planks": "2025-11-21 22:29:27 +0000"
    },
    "done": true
  },
  "refurbished_furniture:recipes/misc/slicing/red_dye_from_poppy": {
    "criteria": {
      "has_poppy": "2025-11-21 23:15:54 +0000"
    },
    "done": true
  },
  "refurbished_furniture:recipes/misc/constructing/birch_table": {
    "criteria": {
      "has_minecraft:birch_planks": "2025-11-21 22:29:27 +0000"
    },
    "done": true
  },
  "refurbished_furniture:recipes/misc/constructing/black_sofa": {
    "criteria": {
      "has_planks": "2025-11-21 22:29:21 +0000"
    },
    "done": true
  },
  "refurbished_furniture:recipes/misc/constructing/light_gray_sofa": {
    "criteria": {
      "has_planks": "2025-11-21 22:29:21 +0000"
    },
    "done": true
  },
  "minecraft:recipes/tools/stone_pickaxe": {
    "criteria": {
      "has_cobblestone": "2025-11-21 22:31:38 +0000"
    },
    "done": true
  },
  "cookingforblockheads:recipes/decorations/tool_rack": {
    "criteria": {
      "has_iron_ingot": "2025-11-21 22:50:54 +0000"
    },
    "done": true
  },
  "minecraft:recipes/misc/black_dye": {
    "criteria": {
      "has_ink_sac": "2025-11-22 01:13:42 +0000"
    },
    "done": true
  },
  "refurbished_furniture:recipes/misc/constructing/frying_pan": {
    "criteria": {
      "has_minecraft:iron_ingot": "2025-11-21 22:50:54 +0000"
    },
    "done": true
  },
  "refurbished_furniture:recipes/misc/constructing/purple_sofa": {
    "criteria": {
      "has_planks": "2025-11-21 22:29:21 +0000"
    },
    "done": true
  },
  "minecraft:recipes/decorations/lantern": {
    "criteria": {
      "has_iron_ingot": "2025-11-21 22:50:54 +0000"
    },
    "done": true
  },
  "minecraft:recipes/decorations/cherry_sign": {
    "criteria": {
      "has_planks": "2025-11-22 02:10:07 +0000"
    },
    "done": true
  },
  "refurbished_furniture:recipes/misc/constructing/spruce_crate": {
    "criteria": {
      "has_minecraft:spruce_planks": "2025-11-21 22:51:02 +0000"
    },
    "done": true
  },
  "farmersdelight:recipes/cooking/beef_stew": {
    "criteria": {
      "has_any_ingredient": "2025-11-21 23:43:47 +0000"
    },
    "done": true
  },
  "waystones:recipes/decorations/blue_sharestone": {
    "criteria": {
      "has_warp_stone": "2025-11-21 23:00:22 +0000"
    },
    "done": true
  },
  "refurbished_furniture:recipes/misc/constructing/pale_oak_lattice_fence": {
    "criteria": {
      "has_minecraft:stick": "2025-11-21 22:28:43 +0000"
    },
    "done": true
  },
  "minecraft:recipes/decorations/campfire": {
    "criteria": {
      "has_stick": "2025-11-21 22:28:43 +0000"
    },
    "done": true
  },
  "refurbished_furniture:recipes/misc/constructing/pale_oak_basin": {
    "criteria": {
      "has_minecraft:iron_ingot": "2025-11-21 22:50:54 +0000"
    },
    "done": true
  },
  "refurbished_furniture:recipes/misc/constructing/dark_oak_lattice_fence": {
    "criteria": {
      "has_minecraft:stick": "2025-11-21 22:28:43 +0000"
    },
    "done": true
  },
  "refurbished_furniture:recipes/misc/constructing/jungle_storage_cabinet": {
    "criteria": {
      "has_minecraft:iron_ingot": "2025-11-21 22:50:54 +0000"
    },
    "done": true
  },
  "farmersdelight:recipes/cooking/dumplings": {
    "criteria": {
      "has_any_ingredient": "2025-11-21 23:44:09 +0000"
    },
    "done": true
  },
  "minecraft:recipes/misc/red_dye_from_beetroot": {
    "criteria": {
      "has_beetroot": "2025-11-21 23:44:45 +0000"
    },
    "done": true
  },
  "minecraft:recipes/misc/sugar_from_sugar_cane": {
    "criteria": {
      "has_sugar_cane": "2025-11-22 01:14:38 +0000"
    },
    "done": true
  },
  "minecraft:recipes/tools/wooden_hoe": {
    "criteria": {
      "has_stick": "2025-11-21 22:28:43 +0000"
    },
    "done": true
  },
  "refurbished_furniture:recipes/misc/constructing/oak_lattice_fence": {
    "criteria": {
      "has_minecraft:stick": "2025-11-21 22:28:43 +0000"
    },
    "done": true
  },
  "refurbished_furniture:recipes/misc/constructing/gray_cooler": {
    "criteria": {
      "has_planks": "2025-11-21 22:29:21 +0000"
    },
    "done": true
  },
  "minecraft:recipes/redstone/oak_fence_gate": {
    "criteria": {
      "has_planks": "2025-11-21 22:29:21 +0000"
    },
    "done": true
  },
  "waystones:recipes/decorations/mossy_waystone": {
    "criteria": {
      "has_warp_stone": "2025-11-21 23:00:22 +0000"
    },
    "done": true
  },
  "refurbished_furniture:recipes/misc/constructing/pale_oak_storage_cabinet": {
    "criteria": {
      "has_minecraft:iron_ingot": "2025-11-21 22:50:54 +0000"
    },
    "done": true
  },
  "refurbished_furniture:recipes/misc/constructing/birch_kitchen_storage_cabinet": {
    "criteria": {
      "has_minecraft:birch_planks": "2025-11-21 22:29:27 +0000"
    },
    "done": true
  },
  "minecraft:recipes/decorations/iron_chain": {
    "criteria": {
      "has_iron_ingot": "2025-11-21 22:50:54 +0000"
    },
    "done": true
  },
  "minecraft:recipes/misc/charcoal": {
    "criteria": {
      "has_log": "2025-11-21 22:27:15 +0000"
    },
    "done": true
  },
  "minecraft:recipes/tools/wooden_pickaxe": {
    "criteria": {
      "has_stick": "2025-11-21 22:28:43 +0000"
    },
    "done": true
  },
  "minecraft:recipes/redstone/cherry_pressure_plate": {
    "criteria": {
      "has_planks": "2025-11-22 02:10:07 +0000"
    },
    "done": true
  },
  "minecraft:recipes/tools/iron_shovel": {
    "criteria": {
      "has_iron_ingot": "2025-11-21 22:50:54 +0000"
    },
    "done": true
  },
  "refurbished_furniture:recipes/misc/constructing/acacia_lattice_fence": {
    "criteria": {
      "has_minecraft:stick": "2025-11-21 22:28:43 +0000"
    },
    "done": true
  },
  "minecraft:recipes/food/cooked_salmon_from_campfire_cooking": {
    "criteria": {
      "has_salmon": "2025-11-21 22:40:32 +0000"
    },
    "done": true
  },
  "farmersdelight:main/root": {
    "criteria": {
      "seeds": "2025-11-21 22:27:15 +0000"
    },
    "done": true
  },
  "farmersdelight:recipes/food/mixed_salad": {
    "criteria": {
      "has_bowl": "2025-11-22 01:27:00 +0000"
    },
    "done": true
  },
  "minecraft:recipes/food/baked_potato_from_smoking": {
    "criteria": {
      "has_potato": "2025-11-22 00:37:17 +0000"
    },
    "done": true
  },
  "minecraft:story/upgrade_tools": {
    "criteria": {
      "stone_pickaxe": "2025-11-21 23:16:57 +0000"
    },
    "done": true
  },
  "refurbished_furniture:recipes/misc/constructing/cherry_cutting_board": {
    "criteria": {
      "has_minecraft:cherry_planks": "2025-11-22 02:10:07 +0000"
    },
    "done": true
  },
  "refurbished_furniture:recipes/misc/constructing/light_gray_stool": {
    "criteria": {
      "has_planks": "2025-11-21 22:29:21 +0000"
    },
    "done": true
  },
  "farmersdelight:main/use_cutting_board": {
    "criteria": {
      "cutting_board": "2025-11-22 00:39:13 +0000"
    },
    "done": true
  },
  "refurbished_furniture:recipes/misc/constructing/white_trampoline": {
    "criteria": {
      "has_minecraft:iron_ingot": "2025-11-21 22:50:54 +0000"
    },
    "done": true
  },
  "refurbished_furniture:recipes/misc/constructing/oak_kitchen_storage_cabinet": {
    "criteria": {
      "has_minecraft:oak_planks": "2025-11-21 22:29:21 +0000"
    },
    "done": true
  },
  "refurbished_furniture:recipes/misc/constructing/white_stool": {
    "criteria": {
      "has_planks": "2025-11-21 22:29:21 +0000"
    },
    "done": true
  },
  "minecraft:recipes/misc/yellow_dye_from_wildflowers": {
    "criteria": {
      "has_wildflowers": "2025-11-21 23:15:43 +0000"
    },
    "done": true
  },
  "refurbished_furniture:recipes/misc/constructing/jungle_light_ceiling_fan": {
    "criteria": {
      "has_minecraft:iron_ingot": "2025-11-21 22:50:54 +0000"
    },
    "done": true
  },
  "minecraft:recipes/redstone/oak_pressure_plate": {
    "criteria": {
      "has_planks": "2025-11-21 22:29:21 +0000"
    },
    "done": true
  },
  "refurbished_furniture:recipes/misc/constructing/birch_kitchen_cabinetry": {
    "criteria": {
      "has_minecraft:birch_planks": "2025-11-21 22:29:27 +0000"
    },
    "done": true
  },
  "refurbished_furniture:recipes/misc/constructing/pale_oak_light_ceiling_fan": {
    "criteria": {
      "has_minecraft:iron_ingot": "2025-11-21 22:50:54 +0000"
    },
    "done": true
  },
  "refurbished_furniture:recipes/misc/constructing/oak_kitchen_cabinetry": {
    "criteria": {
      "has_minecraft:oak_planks": "2025-11-21 22:29:21 +0000"
    },
    "done": true
  },
  "refurbished_furniture:recipes/misc/constructing/orange_grill": {
    "criteria": {
      "has_minecraft:iron_ingot": "2025-11-21 22:50:54 +0000"
    },
    "done": true
  },
  "refurbished_furniture:recipes/misc/constructing/mangrove_lattice_fence": {
    "criteria": {
      "has_minecraft:stick": "2025-11-21 22:28:43 +0000"
    },
    "done": true
  },
  "waystones:recipes/decorations/light_blue_portstone": {
    "criteria": {
      "has_warp_stone": "2025-11-21 23:00:22 +0000"
    },
    "done": true
  },
  "refurbished_furniture:recipes/misc/constructing/cherry_lattice_fence_gate": {
    "criteria": {
      "has_minecraft:stick": "2025-11-21 22:28:43 +0000"
    },
    "done": true
  },
  "refurbished_furniture:recipes/misc/constructing/blue_grill": {
    "criteria": {
      "has_minecraft:iron_ingot": "2025-11-21 22:50:54 +0000"
    },
    "done": true
  },
  "waystones:recipes/decorations/magenta_portstone": {
    "criteria": {
      "has_warp_stone": "2025-11-21 23:00:22 +0000"
    },
    "done": true
  },
  "waystones:recipes/decorations/green_portstone": {
    "criteria": {
      "has_warp_stone": "2025-11-21 23:00:22 +0000"
    },
    "done": true
  },
  "minecraft:recipes/redstone/oak_door": {
    "criteria": {
      "has_planks": "2025-11-21 22:29:21 +0000"
    },
    "done": true
  },
  "waystones:recipes/decorations/orange_portstone": {
    "criteria": {
      "has_warp_stone": "2025-11-21 23:00:22 +0000"
    },
    "done": true
  },
  "moredelight:recipes/cooking/cooked_rice_with_chicken_cuts": {
    "criteria": {
      "has_any_ingredient": "2025-11-21 23:48:45 +0000"
    },
    "done": true
  },
  "refurbished_furniture:recipes/misc/constructing/yellow_stool": {
    "criteria": {
      "has_planks": "2025-11-21 22:29:21 +0000"
    },
    "done": true
  },
  "minecraft:recipes/transportation/carrot_on_a_stick": {
    "criteria": {
      "has_carrot": "2025-11-21 23:43:47 +0000"
    },
    "done": true
  },
  "refurbished_furniture:recipes/misc/slicing/pumpkin_seeds_from_pumpkin": {
    "criteria": {
      "has_pumpkin": "2025-11-21 23:08:26 +0000"
    },
    "done": true
  },
  "farmersdelight:recipes/misc/pumpkin_seeds_from_slice": {
    "criteria": {
      "has_pumpkin_slice": "2025-11-22 00:39:13 +0000"
    },
    "done": true
  },
  "refurbished_furniture:recipes/misc/constructing/oak_desk": {
    "criteria": {
      "has_minecraft:oak_planks": "2025-11-21 22:29:21 +0000"
    },
    "done": true
  },
  "minecraft:recipes/redstone/birch_trapdoor": {
    "criteria": {
      "has_planks": "2025-11-21 22:29:27 +0000"
    },
    "done": true
  },
  "refurbished_furniture:recipes/misc/constructing/black_lamp": {
    "criteria": {
      "has_planks": "2025-11-21 22:29:21 +0000"
    },
    "done": true
  },
  "minecraft:recipes/redstone/spruce_trapdoor": {
    "criteria": {
      "has_planks": "2025-11-21 22:51:02 +0000"
    },
    "done": true
  },
  "comforts:recipes/decorations/shapeless_rope_and_nail": {
    "criteria": {
      "has_iron_ingot": "2025-11-21 22:50:54 +0000"
    },
    "done": true
  },
  "moredelight:recipes/cooking/diced_potatoes_with_porkchop": {
    "criteria": {
      "has_any_ingredient": "2025-11-21 23:48:45 +0000"
    },
    "done": true
  },
  "minecraft:recipes/redstone/spruce_door": {
    "criteria": {
      "has_planks": "2025-11-21 22:51:02 +0000"
    },
    "done": true
  },
  "refurbished_furniture:recipes/misc/constructing/birch_storage_jar": {
    "criteria": {
      "has_minecraft:birch_planks": "2025-11-21 22:29:27 +0000"
    },
    "done": true
  },
  "minecraft:recipes/redstone/spruce_fence_gate": {
    "criteria": {
      "has_planks": "2025-11-21 22:51:02 +0000"
    },
    "done": true
  },
  "minecraft:recipes/combat/golden_sword": {
    "criteria": {
      "has_gold_ingot": "2025-11-21 22:43:27 +0000"
    },
    "done": true
  },
  "minecraft:recipes/tools/wooden_shovel": {
    "criteria": {
      "has_stick": "2025-11-21 22:28:43 +0000"
    },
    "done": true
  },
  "refurbished_furniture:recipes/misc/constructing/light_range_hood": {
    "criteria": {
      "has_minecraft:iron_ingot": "2025-11-21 22:50:54 +0000"
    },
    "done": true
  },
  "minecraft:recipes/redstone/dispenser": {
    "criteria": {
      "has_bow": "2025-11-22 01:06:09 +0000"
    },
    "done": true
  },
  "refurbished_furniture:recipes/misc/constructing/mangrove_light_ceiling_fan": {
    "criteria": {
      "has_minecraft:iron_ingot": "2025-11-21 22:50:54 +0000"
    },
    "done": true
  },
  "minecraft:recipes/building_blocks/cobblestone_slab": {
    "criteria": {
      "has_cobblestone": "2025-11-21 22:31:38 +0000"
    },
    "done": true
  },
  "minecraft:recipes/misc/brick": {
    "criteria": {
      "has_clay_ball": "2025-11-22 00:43:20 +0000"
    },
    "done": true
  },
  "refurbished_furniture:recipes/misc/constructing/post_box": {
    "criteria": {
      "has_planks": "2025-11-21 22:29:21 +0000"
    },
    "done": true
  },
  "refurbished_furniture:recipes/misc/constructing/birch_mail_box": {
    "criteria": {
      "has_minecraft:birch_planks": "2025-11-21 22:29:27 +0000"
    },
    "done": true
  },
  "minecraft:recipes/food/suspicious_stew_from_poppy": {
    "criteria": {
      "has_poppy": "2025-11-21 23:15:54 +0000"
    },
    "done": true
  },
  "minecraft:recipes/building_blocks/gold_block": {
    "criteria": {
      "has_gold_ingot": "2025-11-21 22:43:27 +0000"
    },
    "done": true
  },
  "farmersdelight:recipes/cooking/tomato_sauce": {
    "criteria": {
      "has_tomato": "2025-11-21 22:39:33 +0000"
    },
    "done": true
  },
  "minecraft:recipes/brewing/cauldron": {
    "criteria": {
      "has_water_bucket": "2025-11-21 23:23:44 +0000"
    },
    "done": true
  },
  "farmersdelight:recipes/cooking/ratatouille": {
    "criteria": {
      "has_any_ingredient": "2025-11-21 22:39:33 +0000"
    },
    "done": true
  },
  "refurbished_furniture:recipes/misc/constructing/pink_lamp": {
    "criteria": {
      "has_planks": "2025-11-21 22:29:21 +0000"
    },
    "done": true
  },
  "refurbished_furniture:recipes/misc/constructing/spruce_desk": {
    "criteria": {
      "has_minecraft:spruce_planks": "2025-11-21 22:51:02 +0000"
    },
    "done": true
  },
  "farmersdelight:recipes/misc/tomato_seeds": {
    "criteria": {
      "has_tomato": "2025-11-21 22:39:33 +0000"
    },
    "done": true
  },
  "refurbished_furniture:recipes/misc/constructing/lime_cooler": {
    "criteria": {
      "has_planks": "2025-11-21 22:29:21 +0000"
    },
    "done": true
  },
  "minecraft:recipes/transportation/acacia_boat": {
    "criteria": {
      "in_water": "2025-11-21 22:26:17 +0000"
    },
    "done": true
  },
  "minecraft:recipes/redstone/iron_trapdoor": {
    "criteria": {
      "has_iron_ingot": "2025-11-21 22:50:54 +0000"
    },
    "done": true
  },
  "refurbished_furniture:recipes/misc/constructing/oak_storage_cabinet": {
    "criteria": {
      "has_minecraft:oak_planks": "2025-11-21 22:29:21 +0000"
    },
    "done": true
  },
  "minecraft:adventure/root": {
    "criteria": {
      "killed_something": "2025-11-21 22:25:38 +0000"
    },
    "done": true
  },
  "refurbished_furniture:recipes/misc/constructing/spruce_storage_cabinet": {
    "criteria": {
      "has_minecraft:iron_ingot": "2025-11-21 22:50:54 +0000"
    },
    "done": true
  },
  "enchantplus:weapons/sword/xp_boost": {
    "criteria": {
      "requirement": "2025-11-22 01:06:09 +0000"
    },
    "done": true
  },
  "refurbished_furniture:recipes/misc/constructing/cherry_toilet": {
    "criteria": {
      "has_minecraft:iron_ingot": "2025-11-21 22:50:54 +0000"
    },
    "done": true
  },
  "refurbished_furniture:recipes/misc/constructing/gray_stool": {
    "criteria": {
      "has_planks": "2025-11-21 22:29:21 +0000"
    },
    "done": true
  },
  "refurbished_furniture:recipes/misc/constructing/green_lamp": {
    "criteria": {
      "has_planks": "2025-11-21 22:29:21 +0000"
    },
    "done": true
  },
  "refurbished_furniture:recipes/misc/constructing/spruce_chair": {
    "criteria": {
      "has_minecraft:spruce_planks": "2025-11-21 22:51:02 +0000"
    },
    "done": true
  },
  "farmersdelight:recipes/building_blocks/organic_compost_from_rotten_flesh": {
    "criteria": {
      "has_rotten_flesh": "2025-11-22 01:37:15 +0000"
    },
    "done": true
  },
  "farmersdelight:recipes/building_blocks/rice_bag": {
    "criteria": {
      "has_rice": "2025-11-22 00:40:17 +0000"
    },
    "done": true
  },
  "minecraft:recipes/food/cooked_cod_from_campfire_cooking": {
    "criteria": {
      "has_cod": "2025-11-22 01:13:47 +0000"
    },
    "done": true
  },
  "refurbished_furniture:recipes/misc/constructing/cherry_chair": {
    "criteria": {
      "has_minecraft:cherry_planks": "2025-11-22 02:10:07 +0000"
    },
    "done": true
  },
  "refurbished_furniture:recipes/misc/constructing/cherry_kitchen_drawer": {
    "criteria": {
      "has_minecraft:cherry_planks": "2025-11-22 02:10:07 +0000"
    },
    "done": true
  },
  "refurbished_furniture:recipes/misc/constructing/magenta_sofa": {
    "criteria": {
      "has_planks": "2025-11-21 22:29:21 +0000"
    },
    "done": true
  },
  "betterenchanting:recipes/misc/iron_upgrade_smithing_template": {
    "criteria": {
      "has_iron_ingot": "2025-11-21 22:50:54 +0000"
    },
    "done": true
  },
  "refurbished_furniture:recipes/misc/constructing/acacia_lattice_fence_gate": {
    "criteria": {
      "has_minecraft:stick": "2025-11-21 22:28:43 +0000"
    },
    "done": true
  },
  "refurbished_furniture:recipes/misc/constructing/pink_cooler": {
    "criteria": {
      "has_planks": "2025-11-21 22:29:21 +0000"
    },
    "done": true
  },
  "minecraft:recipes/combat/wooden_sword": {
    "criteria": {
      "has_stick": "2025-11-21 22:28:43 +0000"
    },
    "done": true
  },
  "minecraft:recipes/building_blocks/oak_planks": {
    "criteria": {
      "has_logs": "2025-11-21 22:29:05 +0000"
    },
    "done": true
  },
  "waystones:recipes/decorations/blackstone_waystone": {
    "criteria": {
      "has_warp_stone": "2025-11-21 23:00:22 +0000"
    },
    "done": true
  },
  "minecraft:recipes/tools/iron_axe": {
    "criteria": {
      "has_iron_ingot": "2025-11-21 22:50:54 +0000"
    },
    "done": true
  },
  "minecraft:recipes/combat/crossbow": {
    "criteria": {
      "has_iron_ingot": "2025-11-21 22:50:54 +0000"
    },
    "done": true
  },
  "farmersdelight:recipes/food/shepherds_pie_block": {
    "criteria": {
      "has_cooked_mutton": "2025-11-22 01:57:23 +0000"
    },
    "done": true
  },
  "minecraft:recipes/food/cooked_porkchop_from_smoking": {
    "criteria": {
      "has_porkchop": "2025-11-22 01:13:23 +0000"
    },
    "done": true
  },
  "refurbished_furniture:recipes/misc/constructing/white_sofa": {
    "criteria": {
      "has_planks": "2025-11-21 22:29:21 +0000"
    },
    "done": true
  },
  "waystones:recipes/decorations/pink_portstone": {
    "criteria": {
      "has_warp_stone": "2025-11-21 23:00:22 +0000"
    },
    "done": true
  },
  "minecraft:recipes/misc/iron_nugget_from_blasting": {
    "criteria": {
      "has_iron_leggings": "2025-11-21 22:50:51 +0000"
    },
    "done": true
  },
  "farmersdelight:recipes/food/mutton_wrap": {
    "criteria": {
      "has_mutton": "2025-11-22 01:57:23 +0000"
    },
    "done": true
  },
  "minecraft:adventure/kill_a_mob": {
    "criteria": {
      "minecraft:zombie": "2025-11-21 22:25:38 +0000"
    },
    "done": true
  },
  "minecraft:recipes/transportation/pale_oak_boat": {
    "criteria": {
      "in_water": "2025-11-21 22:26:17 +0000"
    },
    "done": true
  },
  "refurbished_furniture:recipes/misc/constructing/oak_storage_jar": {
    "criteria": {
      "has_minecraft:oak_planks": "2025-11-21 22:29:21 +0000"
    },
    "done": true
  },
  "minecraft:husbandry/plant_any_sniffer_seed": {
    "criteria": {
      "torchflower": "2025-11-22 01:01:18 +0000"
    },
    "done": true
  },
  "farmersdelight:recipes/cooking/beetroot_soup": {
    "criteria": {
      "has_beetroot": "2025-11-21 23:44:45 +0000"
    },
    "done": true
  },
  "minecraft:adventure/adventuring_time": {
    "criteria": {
      "minecraft:old_growth_birch_forest": "2025-11-21 22:26:39 +0000",
      "minecraft:beach": "2025-11-21 22:19:28 +0000",
      "minecraft:forest": "2025-11-21 22:15:49 +0000",
      "minecraft:taiga": "2025-11-21 22:59:18 +0000",
      "minecraft:ocean": "2025-11-22 01:13:52 +0000",
      "minecraft:cherry_grove": "2025-11-21 22:50:36 +0000",
      "minecraft:river": "2025-11-21 22:26:28 +0000",
      "minecraft:lukewarm_ocean": "2025-11-21 22:37:44 +0000",
      "minecraft:birch_forest": "2025-11-21 22:38:47 +0000",
      "minecraft:plains": "2025-11-21 22:24:58 +0000"
    },
    "done": false
  },
  "refurbished_furniture:recipes/misc/constructing/oak_table": {
    "criteria": {
      "has_minecraft:oak_planks": "2025-11-21 22:29:21 +0000"
    },
    "done": true
  },
  "comforts:recipes/decorations/rope_and_nail": {
    "criteria": {
      "has_iron_ingot": "2025-11-21 22:50:54 +0000"
    },
    "done": true
  },
  "minecraft:recipes/decorations/barrel": {
    "criteria": {
      "has_planks": "2025-11-21 22:29:21 +0000"
    },
    "done": true
  },
  "refurbished_furniture:recipes/misc/constructing/oak_cutting_board": {
    "criteria": {
      "has_minecraft:oak_planks": "2025-11-21 22:29:21 +0000"
    },
    "done": true
  },
  "minecraft:husbandry/plant_seed": {
    "criteria": {
      "wheat": "2025-11-21 23:06:25 +0000"
    },
    "done": true
  },
  "minecraft:recipes/decorations/cobblestone_wall_from_cobblestone_stonecutting": {
    "criteria": {
      "has_cobblestone": "2025-11-21 22:31:38 +0000"
    },
    "done": true
  },
  "farmersdelight:recipes/food/sweet_berry_cookie": {
    "criteria": {
      "has_sweet_berries": "2025-11-21 23:01:06 +0000"
    },
    "done": true
  },
  "cookingforblockheads:recipes/decorations/white_fridge": {
    "criteria": {
      "has_iron_ingot": "2025-11-21 22:50:54 +0000"
    },
    "done": true
  },
  "minecraft:recipes/decorations/flower_pot": {
    "criteria": {
      "has_brick": "2025-11-22 00:47:07 +0000"
    },
    "done": true
  },
  "farmersdelight:main/craft_knife": {
    "criteria": {
      "iron_knife": "2025-11-22 00:38:53 +0000"
    },
    "done": true
  },
  "refurbished_furniture:recipes/misc/constructing/cyan_sofa": {
    "criteria": {
      "has_planks": "2025-11-21 22:29:21 +0000"
    },
    "done": true
  },
  "minecraft:recipes/building_blocks/cobblestone_stairs_from_cobblestone_stonecutting": {
    "criteria": {
      "has_cobblestone": "2025-11-21 22:31:38 +0000"
    },
    "done": true
  },
  "refurbished_furniture:recipes/misc/constructing/yellow_cooler": {
    "criteria": {
      "has_planks": "2025-11-21 22:29:21 +0000"
    },
    "done": true
  },
  "refurbished_furniture:recipes/misc/constructing/cherry_kitchen_sink": {
    "criteria": {
      "has_minecraft:cherry_planks": "2025-11-22 02:10:07 +0000"
    },
    "done": true
  },
  "minecraft:recipes/redstone/birch_pressure_plate": {
    "criteria": {
      "has_planks": "2025-11-21 22:29:27 +0000"
    },
    "done": true
  },
  "minecraft:recipes/tools/golden_hoe": {
    "criteria": {
      "has_gold_ingot": "2025-11-21 22:43:27 +0000"
    },
    "done": true
  },
  "moredelight:recipes/food/toast_with_sweet_berries": {
    "criteria": {
      "has_sweet_berries": "2025-11-21 23:01:06 +0000"
    },
    "done": true
  },
  "refurbished_furniture:recipes/misc/constructing/cyan_stool": {
    "criteria": {
      "has_planks": "2025-11-21 22:29:21 +0000"
    },
    "done": true
  },
  "farmersdelight:recipes/decorations/cutting_board": {
    "criteria": {
      "has_stick": "2025-11-21 22:28:43 +0000"
    },
    "done": true
  },
  "refurbished_furniture:recipes/misc/constructing/light_gray_grill": {
    "criteria": {
      "has_minecraft:iron_ingot": "2025-11-21 22:50:54 +0000"
    },
    "done": true
  },
  "refurbished_furniture:recipes/misc/constructing/yellow_grill": {
    "criteria": {
      "has_minecraft:iron_ingot": "2025-11-21 22:50:54 +0000"
    },
    "done": true
  },
  "minecraft:recipes/food/mushroom_stew": {
    "criteria": {
      "has_brown_mushroom": "2025-11-21 23:58:05 +0000"
    },
    "done": true
  },
  "minecraft:husbandry/balanced_diet": {
    "criteria": {
      "suspicious_stew": "2025-11-22 01:39:45 +0000",
      "cooked_cod": "2025-11-22 00:48:39 +0000",
      "cooked_salmon": "2025-11-21 22:49:58 +0000"
    },
    "done": false
  },
  "farmersdelight:recipes/building_blocks/cabbage_crate": {
    "criteria": {
      "has_cabbage": "2025-11-21 23:44:09 +0000"
    },
    "done": true
  },
  "minecraft:recipes/food/cooked_cod": {
    "criteria": {
      "has_cod": "2025-11-22 01:13:47 +0000"
    },
    "done": true
  },
  "minecraft:recipes/building_blocks/cobblestone_stairs": {
    "criteria": {
      "has_cobblestone": "2025-11-21 22:31:38 +0000"
    },
    "done": true
  },
  "refurbished_furniture:recipes/misc/constructing/black_stool": {
    "criteria": {
      "has_planks": "2025-11-21 22:29:21 +0000"
    },
    "done": true
  },
  "refurbished_furniture:recipes/misc/constructing/jungle_toilet": {
    "criteria": {
      "has_minecraft:iron_ingot": "2025-11-21 22:50:54 +0000"
    },
    "done": true
  },
  "farmersdelight:recipes/food/pie_crust": {
    "criteria": {
      "has_wheat": "2025-11-21 23:06:14 +0000"
    },
    "done": true
  },
  "farmersdelight:recipes/combat/iron_knife": {
    "criteria": {
      "has_iron_ingot": "2025-11-21 22:50:54 +0000"
    },
    "done": true
  },
  "refurbished_furniture:recipes/misc/constructing/light_blue_grill": {
    "criteria": {
      "has_minecraft:iron_ingot": "2025-11-21 22:50:54 +0000"
    },
    "done": true
  },
  "farmersdelight:recipes/building_blocks/pumpkin_from_slices": {
    "criteria": {
      "has_pumpkin_slice": "2025-11-22 00:39:13 +0000"
    },
    "done": true
  },
  "refurbished_furniture:recipes/misc/constructing/green_sofa": {
    "criteria": {
      "has_planks": "2025-11-21 22:29:21 +0000"
    },
    "done": true
  },
  "minecraft:recipes/redstone/cherry_door": {
    "criteria": {
      "has_planks": "2025-11-22 02:10:07 +0000"
    },
    "done": true
  },
  "moredelight:recipes/cooking/carrot_soup": {
    "criteria": {
      "has_any_ingredient": "2025-11-21 23:43:47 +0000"
    },
    "done": true
  },
  "waystones:recipes/decorations/pink_sharestone": {
    "criteria": {
      "has_warp_stone": "2025-11-21 23:00:22 +0000"
    },
    "done": true
  },
  "refurbished_furniture:recipes/misc/constructing/cherry_kitchen_storage_cabinet": {
    "criteria": {
      "has_minecraft:cherry_planks": "2025-11-22 02:10:07 +0000"
    },
    "done": true
  },
  "refurbished_furniture:recipes/misc/constructing/blue_cooler": {
    "criteria": {
      "has_planks": "2025-11-21 22:29:21 +0000"
    },
    "done": true
  },
  "refurbished_furniture:recipes/misc/constructing/warped_lattice_fence": {
    "criteria": {
      "has_minecraft:stick": "2025-11-21 22:28:43 +0000"
    },
    "done": true
  },
  "minecraft:recipes/tools/stone_hoe": {
    "criteria": {
      "has_cobblestone": "2025-11-21 22:31:38 +0000"
    },
    "done": true
  },
  "minecraft:recipes/building_blocks/spruce_stairs": {
    "criteria": {
      "has_planks": "2025-11-21 22:51:02 +0000"
    },
    "done": true
  },
  "refurbished_furniture:recipes/misc/constructing/dark_oak_light_ceiling_fan": {
    "criteria": {
      "has_minecraft:iron_ingot": "2025-11-21 22:50:54 +0000"
    },
    "done": true
  },
  "refurbished_furniture:recipes/misc/constructing/orange_cooler": {
    "criteria": {
      "has_planks": "2025-11-21 22:29:21 +0000"
    },
    "done": true
  },
  "refurbished_furniture:recipes/misc/constructing/cherry_light_ceiling_fan": {
    "criteria": {
      "has_minecraft:iron_ingot": "2025-11-21 22:50:54 +0000"
    },
    "done": true
  },
  "refurbished_furniture:recipes/misc/constructing/spruce_drawer": {
    "criteria": {
      "has_minecraft:spruce_planks": "2025-11-21 22:51:02 +0000"
    },
    "done": true
  },
  "refurbished_furniture:recipes/misc/constructing/birch_light_ceiling_fan": {
    "criteria": {
      "has_minecraft:birch_planks": "2025-11-21 22:29:27 +0000"
    },
    "done": true
  },
  "refurbished_furniture:recipes/misc/constructing/yellow_trampoline": {
    "criteria": {
      "has_minecraft:iron_ingot": "2025-11-21 22:50:54 +0000"
    },
    "done": true
  },
  "refurbished_furniture:recipes/misc/constructing/purple_trampoline": {
    "criteria": {
      "has_minecraft:iron_ingot": "2025-11-21 22:50:54 +0000"
    },
    "done": true
  },
  "farmersdelight:recipes/building_blocks/onion_crate": {
    "criteria": {
      "has_onion": "2025-11-21 23:48:45 +0000"
    },
    "done": true
  },
  "refurbished_furniture:recipes/misc/constructing/mangrove_lattice_fence_gate": {
    "criteria": {
      "has_minecraft:stick": "2025-11-21 22:28:43 +0000"
    },
    "done": true
  },
  "refurbished_furniture:recipes/misc/constructing/birch_lattice_fence_gate": {
    "criteria": {
      "has_minecraft:stick": "2025-11-21 22:28:43 +0000"
    },
    "done": true
  },
  "waystones:recipes/decorations/sandy_waystone": {
    "criteria": {
      "has_warp_stone": "2025-11-21 23:00:22 +0000"
    },
    "done": true
  },
  "farmersdelight:recipes/cooking/vegetable_soup": {
    "criteria": {
      "has_any_ingredient": "2025-11-21 23:43:47 +0000"
    },
    "done": true
  },
  "refurbished_furniture:recipes/misc/constructing/birch_desk": {
    "criteria": {
      "has_minecraft:birch_planks": "2025-11-21 22:29:27 +0000"
    },
    "done": true
  },
  "refurbished_furniture:recipes/misc/constructing/recycle_bin": {
    "criteria": {
      "has_minecraft:iron_ingot": "2025-11-21 22:50:54 +0000"
    },
    "done": true
  },
  "waystones:recipes/decorations/waystone": {
    "criteria": {
      "has_warp_stone": "2025-11-21 23:00:22 +0000"
    },
    "done": true
  },
  "refurbished_furniture:recipes/misc/constructing/cyan_lamp": {
    "criteria": {
      "has_planks": "2025-11-21 22:29:21 +0000"
    },
    "done": true
  },
  "cookingforblockheads:recipes/decorations/spice_rack": {
    "criteria": {
      "has_planks": "2025-11-21 22:29:21 +0000"
    },
    "done": true
  },
  "minecraft:recipes/tools/stone_shovel": {
    "criteria": {
      "has_cobblestone": "2025-11-21 22:31:38 +0000"
    },
    "done": true
  },
  "refurbished_furniture:recipes/misc/constructing/light_gray_lamp": {
    "criteria": {
      "has_planks": "2025-11-21 22:29:21 +0000"
    },
    "done": true
  },
  "cookingforblockheads:recipes/decorations/fruit_basket": {
    "criteria": {
      "has_planks": "2025-11-21 22:29:21 +0000"
    },
    "done": true
  },
  "refurbished_furniture:recipes/misc/constructing/gray_sofa": {
    "criteria": {
      "has_planks": "2025-11-21 22:29:21 +0000"
    },
    "done": true
  },
  "farmersdelight:recipes/food/wheat_dough_from_egg": {
    "criteria": {
      "has_wheat": "2025-11-21 23:06:14 +0000"
    },
    "done": true
  },
  "minecraft:recipes/building_blocks/oak_wood": {
    "criteria": {
      "has_log": "2025-11-21 22:29:05 +0000"
    },
    "done": true
  },
  "waystones:recipes/decorations/light_gray_portstone": {
    "criteria": {
      "has_warp_stone": "2025-11-21 23:00:22 +0000"
    },
    "done": true
  },
  "refurbished_furniture:recipes/misc/constructing/magenta_grill": {
    "criteria": {
      "has_minecraft:iron_ingot": "2025-11-21 22:50:54 +0000"
    },
    "done": true
  },
  "minecraft:story/root": {
    "criteria": {
      "crafting_table": "2025-11-21 22:29:33 +0000"
    },
    "done": true
  },
  "refurbished_furniture:recipes/misc/slicing/bread_slice_from_bread": {
    "criteria": {
      "has_bread": "2025-11-22 01:31:01 +0000"
    },
    "done": true
  },
  "refurbished_furniture:recipes/misc/constructing/mangrove_storage_cabinet": {
    "criteria": {
      "has_minecraft:iron_ingot": "2025-11-21 22:50:54 +0000"
    },
    "done": true
  },
  "refurbished_furniture:recipes/misc/constructing/purple_lamp": {
    "criteria": {
      "has_planks": "2025-11-21 22:29:21 +0000"
    },
    "done": true
  },
  "moredelight:recipes/cooking/creamy_pasta_with_ham": {
    "criteria": {
      "has_any_ingredient": "2025-11-21 23:48:45 +0000"
    },
    "done": true
  },
  "minecraft:recipes/redstone/iron_door": {
    "criteria": {
      "has_iron_ingot": "2025-11-21 22:50:54 +0000"
    },
    "done": true
  },
  "moredelight:recipes/cooking/creamy_pasta_with_chicken_cuts": {
    "criteria": {
      "has_any_ingredient": "2025-11-21 23:48:45 +0000"
    },
    "done": true
  },
  "vanillatweaks:name_colors": {
    "criteria": {
      "tick": "2025-11-21 22:15:48 +0000"
    },
    "done": true
  },
  "minecraft:recipes/transportation/jungle_boat": {
    "criteria": {
      "in_water": "2025-11-21 22:26:17 +0000"
    },
    "done": true
  },
  "minecraft:recipes/redstone/heavy_weighted_pressure_plate": {
    "criteria": {
      "has_iron_ingot": "2025-11-21 22:50:54 +0000"
    },
    "done": true
  },
  "refurbished_furniture:recipes/misc/constructing/jungle_lattice_fence_gate": {
    "criteria": {
      "has_minecraft:stick": "2025-11-21 22:28:43 +0000"
    },
    "done": true
  },
  "minecraft:recipes/transportation/dark_oak_boat": {
    "criteria": {
      "in_water": "2025-11-21 22:26:17 +0000"
    },
    "done": true
  },
  "moredelight:main/root": {
    "criteria": {
      "seeds": "2025-11-21 22:27:15 +0000"
    },
    "done": true
  },
  "farmersdelight:main/harvest_ropelogged_tomato": {
    "criteria": {
      "harvest_ropelogged_tomato": "2025-11-21 22:39:32 +0000"
    },
    "done": true
  },
  "refurbished_furniture:recipes/misc/constructing/light_ceiling_light": {
    "criteria": {
      "has_minecraft:iron_ingot": "2025-11-21 22:50:54 +0000"
    },
    "done": true
  },
  "minecraft:recipes/combat/golden_leggings": {
    "criteria": {
      "has_gold_ingot": "2025-11-21 22:43:27 +0000"
    },
    "done": true
  },
  "refurbished_furniture:recipes/misc/constructing/warped_toilet": {
    "criteria": {
      "has_minecraft:iron_ingot": "2025-11-21 22:50:54 +0000"
    },
    "done": true
  },
  "refurbished_furniture:recipes/misc/constructing/pink_stool": {
    "criteria": {
      "has_planks": "2025-11-21 22:29:21 +0000"
    },
    "done": true
  },
  "minecraft:recipes/building_blocks/bone_block": {
    "criteria": {
      "has_bone_meal": "2025-11-21 23:36:40 +0000"
    },
    "done": true
  },
  "DataVersion": 4556
}